{"m_GameObject":{"m_FileID":0,"m_PathID":0},"m_Enabled":1,"m_Script":{"m_FileID":0,"m_PathID":6520365622649918000},"m_Name":"MQ_31_040","vOrderList":[{"eOrder":18,"vsParam":["3016","ウィスティリア","あっ、先輩っ！！\n大丈夫でしたか！？　ケガはありませんか！？","0","","1","wistyria_m_158"]},{"eOrder":18,"vsParam":["1003","マジョラム","そうよ、平気！？\n回復魔法、今すぐかけましょうか！？","3","","","majorum_m_027"]},{"eOrder":18,"vsParam":["3","ソレル","あはは……。大丈夫です、先生。\nもうアニスにかけてもらったんで……","1","","","sorel_m_444"]},{"eOrder":18,"vsParam":["3006","ヘーゼル","それで……。カレンデュラは？","4","","","hazel_m_034"]},{"eOrder":18,"vsParam":["1010","ペパーミント","ふふーん、ボコボコにしてきたよ！\nいやー、見せたかったなぁ、あたしの活躍！","1","","","peppermint_m_495"]},{"eOrder":18,"vsParam":["2005","ホップ","おお、さすが姉御っす！\nやっぱり姉御は最高っすよー！","1","","","hop_m_013"]},{"eOrder":18,"vsParam":["5","クレソン","ウソつけぇ！\nお前、何もしてないだろ！","2","","","cresson_m_239"]},{"eOrder":18,"vsParam":["2001","タンドリオン","クレソン。ペパーミントがお前より働いたからって\nひがむのは……よくないぞ？","0","","","tandrion_m_015"]},{"eOrder":18,"vsParam":["5","クレソン","違っ……！　うう、違うのにぃ……","3","","","cresson_m_240"]},{"eOrder":18,"vsParam":["1004","ルー","外の魔物もあらかた殲滅が終わったよ。\n重傷者はいないようで、何よりだ","0","","","ru_m_031"]},{"eOrder":18,"vsParam":["3008","レディースマントル","んー、なんだかまだ暴れたりないわねぇ……！\nねぇ、あなた。ちょっと一緒にトレーニングしない？","3","","","ladys_m_027"]},{"eOrder":18,"vsParam":["7","ヴァレリアン","遠慮するに決まってんだろ！！\n……[px]、これで借りはひとつ返したからな！","2","","","varerian_m_098"]},{"eOrder":18,"vsParam":["3006","ヘーゼル","こら、そこ、静かにしなさい！　アカデミーの中にいる\n限り、生徒会長には従ってもらうわよ！","2","","","hazel_m_035"]},{"eOrder":18,"vsParam":["2002","シルバーバーチ","はっはっは！　相変わらず怒ったヘーゼルは恐ろしい。\nなぁ、そう思うだろう、ポピーくん？","1","","","silver_m_013"]},{"eOrder":18,"vsParam":["3007","ポピーくん","ノ、ノーコメント……。\n下手なこと言うと、後が怖いしネ……","3","","","popy_m_006"]},{"eOrder":18,"vsParam":["1002","ベルガモット","……ふふ、お疲れ様、[px]。\n今回はお前に助けられてしまったな","1","","","bergamot_m_105"]},{"eOrder":18,"vsParam":["1001","ジョーンズワート","まったくだ。無事で帰ってきてくれて何より。\nアイツは……カレンデュラはまた、行ってしまったか","0","","","Jones_m_040"]},{"eOrder":18,"vsParam":["1001","ジョーンズワート","奴ともいずれまた……いや。\nはは、こっちの話だ","4","","","Jones_m_041"]},{"eOrder":18,"vsParam":["1001","ジョーンズワート","……そうだ、諸君。まだ、帰って来た勇者たちに、\nあの挨拶をしていないのではないかな？","0","","","Jones_m_042"]},{"eOrder":18,"vsParam":["3016","ウィスティリア","あっ、そうでしたそうでした！\nヘーゼル先輩、わたしが音頭取ってもいいですか？","0","","","wistyria_m_159"]},{"eOrder":18,"vsParam":["3006","ヘーゼル","んー、そうね。じゃあ特別に許可するわ。\nでも、噛んだりするんじゃないわよ？","0","","","hazel_m_036"]},{"eOrder":18,"vsParam":["3016","ウィスティリア","あはは、わかってますって。\nそれじゃあ、先輩たちっ！　せーのっ！！","1","","1","wistyria_m_160"]},{"eOrder":18,"vsParam":["","全員","『アカデミーにお帰りなさい！！』","","1","","all_m_015"]},{"eOrder":8,"vsParam":["1"]},{"eOrder":3,"vsParam":["0.5"]},{"eOrder":4,"vsParam":["-1"]},{"eOrder":84,"vsParam":["1"]},{"eOrder":18,"vsParam":["","？？？","んー、あのカレンデュラちんがボロボロにされるとはね。\nあいつら、思ってたよりめんでーなー","","1","","black_m_013"]},{"eOrder":18,"vsParam":["","？？？","まぁ、いっか。あいつらがめんどくても、\nボクちんのやることは変わらないし～","","1","","black_m_014"]},{"eOrder":18,"vsParam":["","？？？","すべてを引っかき回して、すべてを混乱させて……。\nそして、いずれは……","","1","","black_m_015"]},{"eOrder":18,"vsParam":["","？？？","この世の中を、ぜんぶぜーんぶ、壊してやるのさ。\nあひゃ……あひゃひゃひゃひゃ！　あーっひゃひゃひゃ！","","1","","black_m_016"]},{"eOrder":8,"vsParam":["1"]},{"eOrder":84,"vsParam":["0"]}]}
