{"m_GameObject":{"m_FileID":0,"m_PathID":0},"m_Enabled":1,"m_Script":{"m_FileID":0,"m_PathID":6520365622649918000},"m_Name":"CQ_AYE_001","vOrderList":[{"eOrder":92,"vsParam":["1"]},{"eOrder":48,"vsParam":["10","中庭","Courtyard"]},{"eOrder":18,"vsParam":["5010","アーシャ","わぁ、見たことない草やお花がたくさん……。\nこれを使えば、新しいお薬を作れるかも？","1","","3","ayesha_c6_001"]},{"eOrder":18,"vsParam":["1010","ペパーミント","薬を作る……もしかして、錬金術士！？\nえっと……","0","","1","peppermint_c6_233"]},{"eOrder":18,"vsParam":["5010","アーシャ","あ、わたしはアーシャっていいます。\n薬士で、たぶん錬金術士……です","0","","","ayesha_c6_002"]},{"eOrder":18,"vsParam":["4","アニスヒソップ","錬金術士はともかく……薬士、ですか？","0","","2","anis_c6_067"]},{"eOrder":18,"vsParam":["5010","アーシャ","はい。元の世界ではお薬を調合して、\nそのお薬を売っていました","1","","","ayesha_c6_003"]},{"eOrder":20,"vsParam":["「錬金術士と似たようなものかな……？」","「じゃあ薬の専門家ってことだね！」"]},{"eOrder":21,"vsParam":["1"]},{"eOrder":8,"vsParam":["1"]},{"eOrder":98,"vsParam":["hero_c6_093","heroine_c6_093","1"]},{"eOrder":18,"vsParam":["5010","アーシャ","うーん。お薬を専門に作るのが薬士、かなあ？\n実はあんまり錬金術のことを知らなくて……","4","","7","ayesha_c6_004"]},{"eOrder":21,"vsParam":["2"]},{"eOrder":8,"vsParam":["1"]},{"eOrder":98,"vsParam":["hero_c6_094","heroine_c6_094","1"]},{"eOrder":18,"vsParam":["5010","アーシャ","ふふふ、お薬のことなら任せてください。\nすぐに調合しますから","1","","3","ayesha_c6_005"]},{"eOrder":22,"vsParam":[]},{"eOrder":18,"vsParam":["1010","ペパーミント","むむむ、錬金術でも薬は調合するし……\n結局、薬士ってなにが違うんだろ？","4","","2","peppermint_c6_234"]},{"eOrder":18,"vsParam":["4","アニスヒソップ","ええと、アーシャさんは錬金術士でもあるんですよね？\nそれなら、アカデミーで学ぶのはどうでしょうか","1","","2","anis_c6_068"]},{"eOrder":18,"vsParam":["4","アニスヒソップ","錬金術科で学んでいるうちに、\n薬士と錬金術士の違いもはっきりするかもしれません","1","","","anis_c6_069"]},{"eOrder":18,"vsParam":["1010","ペパーミント","あ、そうだね！　いきなりこっちの世界に来ちゃって、\nいる場所がないのも困るだろうし……","4","","1","peppermint_c6_235"]},{"eOrder":18,"vsParam":["5010","アーシャ","いいんですか？　ありがとうございます！\nそっかぁ、この世界にも錬金術があるんだね……","1","","1","ayesha_c6_006"]},{"eOrder":18,"vsParam":["1010","ペパーミント","……って、そういえば異世界に来ちゃったの、\nあんまりびっくりしてないよね！？","3","","6","peppermint_c6_237"]},{"eOrder":18,"vsParam":["5010","アーシャ","あ、えっと。わたし、行方不明になった妹を\n探してるんですけど……","0","","","ayesha_c6_013"]},{"eOrder":18,"vsParam":["5010","アーシャ","手がかりがないか遺跡を調べていて、\n気付いたらここに来ていたんです","3","","7","ayesha_c6_014"]},{"eOrder":18,"vsParam":["5010","アーシャ","だから、遺跡の装置が動き出して\n違うところに来ちゃっただけなのかなって。えへへ……","1","","","ayesha_c6_015"]},{"eOrder":18,"vsParam":["1010","ペパーミント","そ、それもびっくりするところだよね！？\nアーシャってば、のんびり屋さんだなぁ……","3","","6","peppermint_c6_238"]},{"eOrder":18,"vsParam":["5010","アーシャ","あはは、よく言われます……","1","","","ayesha_c6_016"]},{"eOrder":18,"vsParam":["3","ソレル","それにしても、妹さんを探してるって……\n大変なときにこっちへ来ちゃったわね","4","","7","sorel_c6_098"]},{"eOrder":18,"vsParam":["5010","アーシャ","あ、そのことなんですけど……。もしかしたら、\n妹もこうして違う世界に来ているのかなって","2","","","ayesha_c6_017"]},{"eOrder":18,"vsParam":["5010","アーシャ","だから、元の世界に帰る方法を探していたら、\nどこかで会えるかも……！","0","","1","ayesha_c6_018"]},{"eOrder":18,"vsParam":["1010","ペパーミント","そっか……うん、アタシたちも応援するよ！\nこれからよろしくね、アーシャ！","1","","","peppermint_c6_239"]},{"eOrder":18,"vsParam":["5010","アーシャ","はい！　みなさん、よろしくお願いします！","1","","4","ayesha_c6_019"]},{"eOrder":8,"vsParam":["1"]},{"eOrder":49,"vsParam":[]},{"eOrder":92,"vsParam":["0"]}]}
