{"m_GameObject":{"m_FileID":0,"m_PathID":0},"m_Enabled":1,"m_Script":{"m_FileID":0,"m_PathID":6520365622649918000},"m_Name":"CQ_SUE_007","vOrderList":[{"eOrder":4,"vsParam":["9"]},{"eOrder":18,"vsParam":["5004","スール","ふふふ……。\nふははははは……！","1","","3","suelle_c2_106"]},{"eOrder":18,"vsParam":["4","アニスヒソップ","ど、どうしたんですか、スーさん……。\nノートを片手に、高笑いしたりして……","4","","2"]},{"eOrder":18,"vsParam":["5004","スール","今度こそ完璧な野望ができてしまった……。\nこれをこなせば、国一番にぐっと近付くよ！","0","","","suelle_c2_107"]},{"eOrder":18,"vsParam":["5","クレソン","はぁ、完璧な野望ねぇ……。\n今度はどんなのなんだ？","1","","","cresson_c2_137"]},{"eOrder":18,"vsParam":["5004","スール","ずばり！\n『錬金術士として真面目に仕事する』だよ！","1","","","suelle_c2_108"]},{"eOrder":18,"vsParam":["3","ソレル","ええええっ、普通！？\nスーなのに普通じゃない！　一体どうしたの！？","2","","1"]},{"eOrder":18,"vsParam":["5004","スール","ふふふ……あたし、思ったんだよね。\n……この世界、奇をてらっても失敗するだけだって","0","","","suelle_c2_109"]},{"eOrder":18,"vsParam":["4","アニスヒソップ","あ、ああ……。\nそれは……なんとも言えませんね……","4"]},{"eOrder":18,"vsParam":["5004","スール","だから、真面目に調合でもしようかなーって。\nでも、材料がぜーんぜん足りないんだよねー","4","","","suelle_c2_110"]},{"eOrder":18,"vsParam":["5004","スール","……というわけで、[px]さん！\n……きゃはっ★","1","","4","suelle_c2_111"]},{"eOrder":18,"vsParam":["5","クレソン","……材料を採ってこい、と。\nどうするんだ、[px]","0","","","cresson_c2_138"]},{"eOrder":20,"vsParam":["「きゃはっ★」","「しょうがないなぁ」"]},{"eOrder":21,"vsParam":["1"]},{"eOrder":8,"vsParam":["1"]},{"eOrder":98,"vsParam":["hero_c2_213","heroine_c2_213","1"]},{"eOrder":18,"vsParam":["5004","スール","……よし、それは肯定ってことだよね！\nじゃ、メモはここにあるから！","0","","","suelle_c2_112"]},{"eOrder":21,"vsParam":["2"]},{"eOrder":8,"vsParam":["1"]},{"eOrder":98,"vsParam":["hero_c2_214","heroine_c2_214","1"]},{"eOrder":18,"vsParam":["5004","スール","ふふ、ありがとう、[px]さん！\nじゃ、メモはここにあるから！","0","","","suelle_c2_113"]},{"eOrder":22,"vsParam":[]},{"eOrder":18,"vsParam":["5004","スール","あたしの国一番の野望のために！\n材料調達、よろしくねっ！！","1","","3","suelle_c2_114"]},{"eOrder":8,"vsParam":["1"]},{"eOrder":1,"vsParam":["0","","1"]},{"eOrder":3,"vsParam":["1"]},{"eOrder":6,"vsParam":["66","0"]},{"eOrder":3,"vsParam":["0.25"]},{"eOrder":6,"vsParam":["66","0"]},{"eOrder":3,"vsParam":["1"]},{"eOrder":6,"vsParam":["66","1"]},{"eOrder":3,"vsParam":["0.5"]},{"eOrder":95,"vsParam":["82"]},{"eOrder":1,"vsParam":["1","","1"]},{"eOrder":18,"vsParam":["5004","スール","わぁ、ありがとう、[px]さん！\n頼んでた材料、持ってきてくれたんだね！","1","","3","suelle_c2_115"]},{"eOrder":18,"vsParam":["5004","スール","くふふ、それじゃあ早速……！\nあたしの調合テクニック、お見せするとしますかー！","0","","","suelle_c2_116"]},{"eOrder":18,"vsParam":["1010","ペパーミント","えーと……。スー、大丈夫？\n[px]が手伝わなくても平気？","4"]},{"eOrder":18,"vsParam":["5004","スール","大丈夫だって！\nふふーん、終わったら呼ぶから、ちょっと待っててよ！","1","","","suelle_c2_117"]},{"eOrder":18,"vsParam":["5","クレソン","うーん、ちょっと不安だが、わかった……","1","","","cresson_c2_139"]},{"eOrder":8,"vsParam":["1"]},{"eOrder":1,"vsParam":["0","","1"]},{"eOrder":6,"vsParam":["83","0"]},{"eOrder":3,"vsParam":["2"]},{"eOrder":6,"vsParam":["83","0"]},{"eOrder":3,"vsParam":["1"]},{"eOrder":1,"vsParam":["1","","1"]},{"eOrder":18,"vsParam":["5004","スール","よーし、ひとまず終わりー！\nみんな、できたよー！","1","","","suelle_c2_118"]},{"eOrder":18,"vsParam":["3","ソレル","ふふふ、とりあえず爆発はさせなかったみたいね。\nそれじゃ、お手並み拝見と……って、これ……！","0"]},{"eOrder":18,"vsParam":["5","クレソン","本当にスーが作ったのか！？\n[px]の道具とも大差ねぇぞ？","2","","1","cresson_c2_140"]},{"eOrder":18,"vsParam":["5004","スール","ふふーん、そうだよ！\n未熟とはいえ、だてに国一番を目指してないからねー","1","","3","suelle_c2_119"]},{"eOrder":18,"vsParam":["4","アニスヒソップ","すごいです、スーさん！\nこれなら、評判だってうなぎ登りですよ！","1"]},{"eOrder":18,"vsParam":["5004","スール","でしょでしょー？\nもっと褒めて、もっと褒めて！！","1","","4","suelle_c2_120"]},{"eOrder":20,"vsParam":["「スーは天才だよ！」","「お見それしました！」"]},{"eOrder":21,"vsParam":["1"]},{"eOrder":8,"vsParam":["1"]},{"eOrder":98,"vsParam":["hero_c2_215","heroine_c2_215","1"]},{"eOrder":21,"vsParam":["2"]},{"eOrder":8,"vsParam":["1"]},{"eOrder":98,"vsParam":["hero_c2_216","heroine_c2_216","1"]},{"eOrder":22,"vsParam":[]},{"eOrder":18,"vsParam":["5004","スール","くふふ♪\nこれで、みんなもあたしのこと、見直したかな？","1","","3","suelle_c2_121"]},{"eOrder":18,"vsParam":["5","クレソン","うーむ、なんだかんだ言って、\nスーの調合を見るのはこれが初めてだからな……","1","","","cresson_c2_141"]},{"eOrder":18,"vsParam":["3","ソレル","そうね……。スーがここまでの実力者だったとは。\n本当に驚いたわ","0"]},{"eOrder":18,"vsParam":["1010","ペパーミント","だね……。\n……もしかして、ズルした？","0"]},{"eOrder":18,"vsParam":["5004","スール","してないよっ！！\nでもまぁ、この調子なら大丈夫そうかな","2","","1","suelle_c2_122"]},{"eOrder":18,"vsParam":["5004","スール","くふふ、錬金術できっちり仕事をこなして、\nあっという間に国一番になってやる……！","1","","3","suelle_c2_123"]},{"eOrder":8,"vsParam":["1"]},{"eOrder":4,"vsParam":["-1"]},{"eOrder":95,"vsParam":["0"]}]}
