{"m_GameObject":{"m_FileID":0,"m_PathID":0},"m_Enabled":1,"m_Script":{"m_FileID":0,"m_PathID":6520365622649918000},"m_Name":"EV_043_021_010","vOrderList":[{"eOrder":18,"vsParam":["1010","ペパーミント","えっと、あの、リディー。\nはい、これ……『水断ち粘土』だよ","4"]},{"eOrder":18,"vsParam":["5003","リディー","ありがとうございます！\nうん。これくらいあれば、うちの雨漏りもなんとかなるかな","1"]},{"eOrder":18,"vsParam":["1010","ペパーミント","……あのさ。\nリディーのうちの雨漏り、そんなにひどいの？","3"]},{"eOrder":18,"vsParam":["5003","リディー","あっ……だ、大丈夫ですよ！\nそこまでボロボロってわけじゃないんです！","3"]},{"eOrder":18,"vsParam":["5003","リディー","いや、実は結構ボロボロではあるんですけど。\nでも、雨漏りし始めた原因は、その……","3"]},{"eOrder":18,"vsParam":["5003","リディー","私とスーちゃんが、錬金術を失敗して……。\n爆発して飛び散った材料が、屋根を貫通して……","4"]},{"eOrder":18,"vsParam":["1010","ペパーミント","あ、ああ……。\n錬金術士にはよくある……よくあるのかな？","4"]},{"eOrder":18,"vsParam":["5003","リディー","わ、わからないですけど……。\nと、とにかくそういうことなので！","2"]},{"eOrder":18,"vsParam":["1010","ペパーミント","それならよかった。リディーの家、\nそんなにボロっちいのかって心配しちゃったよ","1"]},{"eOrder":18,"vsParam":["5003","リディー","すみません、ご心配かけちゃって。\n本当にそこまでではないので、大丈夫です！","1"]},{"eOrder":18,"vsParam":["5003","リディー","……いや、実はダメなのかも。\n床はきしむし、隙間風はすごいし……","4"]},{"eOrder":18,"vsParam":["5003","リディー","これも元はといえば、修理代に貯めておいたお金を\nお父さんが使い込むから……ふふ……ふふふ……","1"]},{"eOrder":18,"vsParam":["1010","ペパーミント","あっ、やばい！\n踏み込んじゃいけないところだった気がする！","4"]},{"eOrder":18,"vsParam":["1010","ペパーミント","み、『水断ち粘土』は確かに渡したからね～！\nそれじゃ、またね、リディー……あははははー……","4"]},{"eOrder":18,"vsParam":["5003","リディー","元の世界に帰ったら、まずは……。\nうーん、こっちの世界である程度お金を……む～……","3"]},{"eOrder":8,"vsParam":["1"]}]}
