{"m_GameObject":{"m_FileID":0,"m_PathID":0},"m_Enabled":1,"m_Script":{"m_FileID":0,"m_PathID":6520365622649918000},"m_Name":"SQ_SUB_05_010","vOrderList":[{"eOrder":18,"vsParam":["9004","少年","はぁ、困った……"]},{"eOrder":18,"vsParam":["1010","ペパーミント","む、悩める少年発見！\r\nどったのどったの？"]},{"eOrder":18,"vsParam":["9004","少年","え……？　いや、オレ画家になりたいんだけどさ。\r\n……ないんだよ"]},{"eOrder":18,"vsParam":["3","ソレル","ない……？\r\nないって、なにが？"]},{"eOrder":18,"vsParam":["9004","少年","金がないんだよ！　それは置いといても、紙がないんだよ！\r\nそこらに絵を描き殴るわけにもいかないだろ？"]},{"eOrder":18,"vsParam":["9004","少年","だから、絵の練習ができなくて悩んでるというわけさ。\r\n頭抱えちまうよ、ちくしょー！"]},{"eOrder":18,"vsParam":["1010","ペパーミント","ふーん、なるほどねぇ……。\r\nじゃあここは、[px]が一肌脱ぎましょう！"]},{"eOrder":18,"vsParam":["9004","少年","え……？　どういうことだ？\r\nあんたの服に、絵を描いてもいいのか！？"]},{"eOrder":18,"vsParam":["4","アニスヒソップ","い、いえ、さすがにそれは……。\r\nええと、[px]さんは錬金術士なんですよ"]},{"eOrder":18,"vsParam":["4","アニスヒソップ","だから、[px]さんに任せれば……ふふっ♪"]},{"eOrder":18,"vsParam":["3","ソレル","紙だろうが絵の具だろうが、自由自在ってわけ！\r\nいけるわよね、[px]？"]},{"eOrder":20,"vsParam":["「もちろん！」","「なんとかしましょう」"]},{"eOrder":21,"vsParam":["1"]},{"eOrder":21,"vsParam":["2"]},{"eOrder":22,"vsParam":[]},{"eOrder":18,"vsParam":["1010","ペパーミント","ふふー、それでこそ[px]！\r\n未来の大錬金術士！"]},{"eOrder":18,"vsParam":["9004","少年","そっか……！　そいつは助かる！\r\nじゃあ紙の準備を頼んだぜ、未来の大錬金術士さん！"]}]}
