{"m_GameObject":{"m_FileID":0,"m_PathID":0},"m_Enabled":1,"m_Script":{"m_FileID":0,"m_PathID":6520365622649918000},"m_Name":"SQ_SUB_027_010","vOrderList":[{"eOrder":48,"vsParam":["204","ローズヒップ邸"]},{"eOrder":18,"vsParam":["1010","ペパーミント","ローズヒップー！\r\nちょっと聞きたいことがあるんだけど……あれ？　いない？","2","","2"]},{"eOrder":18,"vsParam":["1022","ネトル","あ、お姉ちゃんたち！\r\nローズヒップさまなら、お部屋で休んでるよ","1","","1"]},{"eOrder":18,"vsParam":["1022","ネトル","なんか、身体の具合がよくないんだって。\r\nちょっと心配だね……","0","","7"]},{"eOrder":18,"vsParam":["6","アンゼリカ","そうなんだ……。ねぇ、ネトル。\r\n領主様が部屋で休むのは、よくあることなの？","4","","2"]},{"eOrder":18,"vsParam":["1022","ネトル","うん……。\r\n何日かごとに、部屋にこもりっきりになっちゃう……","0"]},{"eOrder":18,"vsParam":["1022","ネトル","その間は、メイドさんとか執事さんが\r\nぼくと遊んでくれるんだけどね……？","0"]},{"eOrder":18,"vsParam":["6","アンゼリカ","……そっか、それは安心した。\r\nでも、ローズヒップ様の身体は心配……","0"]},{"eOrder":18,"vsParam":["4","アニスヒソップ","そうですね……。\r\nよほど具合が悪いのでしょうか……","3"]},{"eOrder":18,"vsParam":["5","クレソン","そうだ、[px]！\r\nローズヒップ様を元気にする薬、作れねぇかな？","1","","2"]},{"eOrder":18,"vsParam":["3","ソレル","あっ、そうね。それがいいわ。\r\n錬金術なら、きっとできるもの！","0","","1"]},{"eOrder":18,"vsParam":["1022","ネトル","本当！？　ねぇ、[px]さん！\r\nローズヒップさまのために、お薬をお願いしてもいい？","1","","1"]},{"eOrder":20,"vsParam":["「もちろん！」","「頑張るよ！」"]},{"eOrder":21,"vsParam":["1"]},{"eOrder":21,"vsParam":["2"]},{"eOrder":22,"vsParam":[]},{"eOrder":18,"vsParam":["1022","ネトル","ありがとう！\r\nそれじゃあ、よろしくお願いします！","1","","3"]},{"eOrder":8,"vsParam":["1"]},{"eOrder":49,"vsParam":[]}]}
