{"m_GameObject":{"m_FileID":0,"m_PathID":0},"m_Enabled":1,"m_Script":{"m_FileID":0,"m_PathID":6520365622649918000},"m_Name":"CQ_ANS_001_020","vOrderList":[{"eOrder":18,"vsParam":["1010","Peppermint","Anise! I've prepared the item you asked for.\nHere you are!","0"]},{"eOrder":18,"vsParam":["4","Anise Hyssop","Wow... Thank you very much!\nThis flower should be able to bounce back!","1"]},{"eOrder":6,"vsParam":["71","0"]},{"eOrder":86,"vsParam":["1","20"]},{"eOrder":18,"vsParam":["4","Anise Hyssop","Let's try it.","0"]},{"eOrder":18,"vsParam":["4","Anise Hyssop","Mix the \"Round Feces\" into the soil...\nAnd then water the flower...","2"]},{"eOrder":18,"vsParam":["1010","Peppermint","(Swallowing)...","2"]},{"eOrder":8,"vsParam":["1"]},{"eOrder":6,"vsParam":["28","0"]},{"eOrder":86,"vsParam":["1","21"]},{"eOrder":3,"vsParam":["1"]},{"eOrder":86,"vsParam":["1","22"]},{"eOrder":3,"vsParam":["1"]},{"eOrder":18,"vsParam":["4","Anise Hyssop","Wow, so impressive!\nLook, it blooms!","1"]},{"eOrder":18,"vsParam":["1010","Peppermint","Wow, it works!","1"]},{"eOrder":20,"vsParam":["It's wonderful to see the flower flourishing again","A piece of cake!"]},{"eOrder":21,"vsParam":["1"]},{"eOrder":18,"vsParam":["4","Anise Hyssop","Thank you so much!\nYou really are a big help!","0"]},{"eOrder":21,"vsParam":["2"]},{"eOrder":18,"vsParam":["1010","Peppermint","Ha ha, no need for bravado.\nJust take the compliment and be happy about it. Look, look.","1"]},{"eOrder":18,"vsParam":["4","Anise Hyssop","Hehe, thank you so much,\n[px]. You really are a big help!","1"]},{"eOrder":22,"vsParam":[]},{"eOrder":86,"vsParam":["0"]},{"eOrder":18,"vsParam":["4","Anise Hyssop","I'm going to hand in the investigation report to Ru Sensei.\n[px], you guys should come with me.","0"]},{"eOrder":18,"vsParam":["4","Anise Hyssop","And I want to tell Ru Sensei the truth that\nif it weren't for the help of [px] and Peppermint...","0"]},{"eOrder":8,"vsParam":["1"]},{"eOrder":1,"vsParam":["0"]},{"eOrder":3,"vsParam":["0.4"]},{"eOrder":1,"vsParam":["1"]},{"eOrder":48,"vsParam":["6","Class Room","Class Room"]},{"eOrder":18,"vsParam":["1004","Ru","...","0"]},{"eOrder":18,"vsParam":["4","Anise Hyssop","So, Sensei...\nHow's my work?","0"]},{"eOrder":18,"vsParam":["1004","Ru","Well...\nI'll give you a pass if I only look at the report itself.","0"]},{"eOrder":20,"vsParam":["Only look at the \"report itself\"?","This assignment is deliberately making things difficult."]},{"eOrder":21,"vsParam":["1"]},{"eOrder":18,"vsParam":["1004","Ru","Oh?\n[px] noticed that, huh?","0"]},{"eOrder":21,"vsParam":["2"]},{"eOrder":18,"vsParam":["1004","Ru","Ha ha, don't get upset.\nI also have my own concerns.","0"]},{"eOrder":22,"vsParam":[]},{"eOrder":18,"vsParam":["1004","Ru","I'm sorry, Anise.\nThis assignment was meant to challenge you.","0"]},{"eOrder":18,"vsParam":["4","Anise Hyssop","What?\nWhat do you mean...","0"]},{"eOrder":18,"vsParam":["1004","Ru","I purposely gave you a malnourished plant.\nI just wanted to see how you would handle the assignment.","0"]},{"eOrder":18,"vsParam":["1010","Peppermint","Oh, so this assignment was actually a test for Anise?","4"]},{"eOrder":18,"vsParam":["1004","Ru","You are brilliant, and you stand out among all the\napprentice sages I've instructed and supervised.","0"]},{"eOrder":18,"vsParam":["1004","Ru","Nevertheless, you will sooner or later encounter difficulties.\nThis is very common for a sage who studies the unknown.","0"]},{"eOrder":18,"vsParam":["1004","Ru","I designed this assignment to see...\nhow you would react when you run into such a problem.","0"]},{"eOrder":18,"vsParam":["1010","Peppermint","Wow...\nRu Sensei, that was mean...","3"]},{"eOrder":18,"vsParam":["1004","Ru","Humph, I'm just doing what a teacher should do.\nThat doesn't make me a bad person.","0"]},{"eOrder":18,"vsParam":["4","Anise Hyssop","Hehe, thank you, Ru Sensei.\nNow I get it... the purpose of this assignment.","1"]},{"eOrder":18,"vsParam":["1004","Ru","OK. Now please excuse me.\nI have to get back to continue my research.","0"]},{"eOrder":18,"vsParam":["1010","Peppermint","Hmm, that was pretty complicated...\nBut it's great that we've finished the assignment, right?","0"]},{"eOrder":18,"vsParam":["4","Anise Hyssop","That's right...\nI couldn't have done it without [px] and Peppermint.","1"]},{"eOrder":18,"vsParam":["4","Anise Hyssop","However, my ecological survey is not over.\nAlso, to begin with, I didn't see the true purpose of the assignment.","0"]},{"eOrder":18,"vsParam":["4","Anise Hyssop","Next time I hand in an assignment it will be perfect!\nI'll have to work even harder to do so!","2"]},{"eOrder":18,"vsParam":["1010","Peppermint","Ha ha ha... that's Anise...\nIt's good to be diligent, but don't overwork yourself!","0"]},{"eOrder":8,"vsParam":["1"]},{"eOrder":49,"vsParam":[]}]}
