{"m_GameObject":{"m_FileID":0,"m_PathID":0},"m_Enabled":1,"m_Script":{"m_FileID":0,"m_PathID":6520365622649918000},"m_Name":"CQ_AMA_006_010","vOrderList":[{"eOrder":18,"vsParam":["3","Sorel","Everyone, something is very wrong!\nA powerful monster showed up!","2"]},{"eOrder":18,"vsParam":["5","Cresson","It's pretty powerful...\nAnd the guards can't seem to defeat it.","2"]},{"eOrder":18,"vsParam":["5016","Amaryllis","Such a powerful monster...!?\nHmm. It's a toughie...","2","","1"]},{"eOrder":18,"vsParam":["5016","Amaryllis","Alright, everyone! Let's go take it down together!!","0"]},{"eOrder":18,"vsParam":["5","Cresson","OK! It's near the Mermaid Rock.\nLet's go there and defeat it!","1"]},{"eOrder":18,"vsParam":["5016","Amaryllis","Mermaid Rock...?\nNo way.","2"]},{"eOrder":8,"vsParam":["1"]}]}
