{"m_GameObject":{"m_FileID":0,"m_PathID":0},"m_Enabled":1,"m_Script":{"m_FileID":0,"m_PathID":6520365622649918000},"m_Name":"CQ_NEL_003","vOrderList":[{"eOrder":92,"vsParam":["1"]},{"eOrder":4,"vsParam":["9"]},{"eOrder":48,"vsParam":["1","Atelier [px]","Atelier"]},{"eOrder":18,"vsParam":["5009","Nelke","Ah, [px]?\nIs that...","2","","1","nelke_c5_040"]},{"eOrder":18,"vsParam":["1010","Peppermint","Hey, Nelke!\nWe are sorting our alchemy recipes!","1","","1"]},{"eOrder":18,"vsParam":["5009","Nelke","Ah, so I guessed correctly!\nCan I take a look?","1","","3","nelke_c5_041"]},{"eOrder":18,"vsParam":["1010","Peppermint","Uh? Of course you can...\nAre you interested in alchemy too?","0","","2"]},{"eOrder":18,"vsParam":["5009","Nelke","Yeah! My world also has alchemy,\nand there are many alchemists from different worlds...","1","","1","nelke_c5_042"]},{"eOrder":18,"vsParam":["5009","Nelke","The development of Westwald relies on alchemy,\nso I'm quite familiar with it.","0","","","nelke_c5_043"]},{"eOrder":18,"vsParam":["1010","Peppermint","Wow!\nThere are alchemists in your world, too!","1","","1"]},{"eOrder":18,"vsParam":["5009","Nelke","Yes... Uh, [px]! If you don't mind,\ncan you make something for me to see?","0","","","nelke_c5_044"]},{"eOrder":18,"vsParam":["5009","Nelke","I want to see\nthis world's alchemy!","1","","1","nelke_c5_045"]},{"eOrder":18,"vsParam":["1010","Peppermint","Er, sure!\nRight, [px]!","0","","1"]},{"eOrder":8,"vsParam":["1"]},{"eOrder":1,"vsParam":["0","1"]},{"eOrder":3,"vsParam":["0.5"]},{"eOrder":6,"vsParam":["83","0"]},{"eOrder":3,"vsParam":["1"]},{"eOrder":6,"vsParam":["83","0"]},{"eOrder":3,"vsParam":["1"]},{"eOrder":1,"vsParam":["1","1"]},{"eOrder":18,"vsParam":["1010","Peppermint","Done! How's that?\nThis is the alchemy in our world!","1","","3"]},{"eOrder":18,"vsParam":["5009","Nelke","Uh, you also use alchemical Cauldron here... So the\ndifference is only the names of items and ingredients?","2","","","nelke_c5_046"]},{"eOrder":18,"vsParam":["5009","Nelke","The item you made seems to be different, too...\nLooks like some in-depth study is needed!","2","","1","nelke_c5_047"]},{"eOrder":20,"vsParam":["You are like Sensei Ru...","I am glad to make you happy!"]},{"eOrder":21,"vsParam":["1"]},{"eOrder":8,"vsParam":["1"]},{"eOrder":98,"vsParam":["hero_c5_047","heroine_c5_047","1"]},{"eOrder":18,"vsParam":["5009","Nelke","Ah, I'm sorry!\nI lost in thought...","1","","7","nelke_c5_048"]},{"eOrder":21,"vsParam":["2"]},{"eOrder":8,"vsParam":["1"]},{"eOrder":98,"vsParam":["hero_c5_048","heroine_c5_048","1"]},{"eOrder":18,"vsParam":["5009","Nelke","Yeah! Thank you, [px]!\nYou just showed me something very interesting.","1","","3","nelke_c5_049"]},{"eOrder":22,"vsParam":[]},{"eOrder":18,"vsParam":["1010","Peppermint","Ha ha! Nelke,\nyou are really into alchemy!","1"]},{"eOrder":18,"vsParam":["5009","Nelke","Sorry... I always get too excited to notice anything else\nin my surroundings when talking alchemy...","1","","6","nelke_c5_050"]},{"eOrder":18,"vsParam":["1010","Peppermint","[px] is also like that.\nBut, why do you like alchemy so much, Nelke?","0","","2"]},{"eOrder":18,"vsParam":["5009","Nelke","Um... There's a person called \"the Sage of Granzweit\"\nin the world where I come from.","0","","","nelke_c5_051"]},{"eOrder":18,"vsParam":["5009","Nelke","This sage traveled all over the world and helped people with\nalchemy... There're great stories about the sage in many places.","1","","","nelke_c5_052"]},{"eOrder":18,"vsParam":["5009","Nelke","When I heard about these stories,\nI became attracted to sages and alchemy.","1","","4","nelke_c5_053"]},{"eOrder":18,"vsParam":["1010","Peppermint","Oh, I see!\nWhy don't you study alchemy too?","1","","3"]},{"eOrder":18,"vsParam":["5009","Nelke","Um... Sorry.\nI can't use alchemy...","4","","6","nelke_c5_054"]},{"eOrder":18,"vsParam":["1010","Peppermint","Ah... My apologies. I said silly things...","4","","7"]},{"eOrder":18,"vsParam":["5009","Nelke","Ho ho, never mind. Even if I can't use alchemy,\nI'll make contributions to people in other forms!","1","","3","nelke_c5_055"]},{"eOrder":18,"vsParam":["1010","Peppermint","Wow...\nYou are so cool, Nelke!","0"]},{"eOrder":18,"vsParam":["1010","Peppermint","In order to help other people,\nwe must work harder!","1","","1"]},{"eOrder":8,"vsParam":["1"]},{"eOrder":4,"vsParam":["-1"]},{"eOrder":49,"vsParam":[]},{"eOrder":92,"vsParam":["0"]}]}
