{"m_GameObject":{"m_FileID":0,"m_PathID":0},"m_Enabled":1,"m_Script":{"m_FileID":0,"m_PathID":6520365622649918000},"m_Name":"MQ_20_050","vOrderList":[{"eOrder":92,"vsParam":["0"]},{"eOrder":95,"vsParam":["92"]},{"eOrder":92,"vsParam":["1"]},{"eOrder":18,"vsParam":["5","Cresson","Phew, finally we took it down... Huh?","1","","","cresson_m_177"]},{"eOrder":4,"vsParam":["9"]},{"eOrder":18,"vsParam":["3002","???","However the times change~♪\nYou're always my only love~♪","0","","3","amariris_m_002"]},{"eOrder":18,"vsParam":["5","Cresson","Even though it's off key... That fish tail...\nRight, it's a mermaid!","1","","","cresson_m_178"]},{"eOrder":18,"vsParam":["1010","Peppermint","Hey~ The mermaid over there~ Um.\nThe mermaid over there!","0","","","peppermint_m_367"]},{"eOrder":18,"vsParam":["3","Sorel","\"The mermaid over there!\" It sounds so weird!\nUm, excuse us, could you please tell us...","1","","6","sorel_m_364"]},{"eOrder":18,"vsParam":["3002","Amaryllis","... Huh? Oh, human, so rare!\nHehe, my name is Amaryllis, just call me that, OK?","0","","1","amariris_m_003"]},{"eOrder":18,"vsParam":["4","Anise Hyssop","Ah, OK... Amaryllis.\nYou live here?","4","","2","anis_m_244"]},{"eOrder":18,"vsParam":["3002","Amaryllis","Yes. I used to live somewhere named \"Mermaid Rock\",\nbut it collapsed, not suitable for living anymore.","4","","","amariris_m_004"]},{"eOrder":18,"vsParam":["3002","Amaryllis","All the other mermaids have moved away, but I... Um...","0","","","amariris_m_005"]},{"eOrder":8,"vsParam":["1"]},{"eOrder":23,"vsParam":["1"]},{"eOrder":95,"vsParam":["90"]},{"eOrder":26,"vsParam":[]},{"eOrder":95,"vsParam":["89"]},{"eOrder":27,"vsParam":[]},{"eOrder":18,"vsParam":["","Amaryllis","I can't get over a man who I just met once...\n\"That handsome man\"... Hehe.","","1","","amariris_m_006"]},{"eOrder":18,"vsParam":["","Angelica","\"That handsome man\"...\nShe meant Lord Rod?","","1","","angelica_m_162"]},{"eOrder":18,"vsParam":["","Sorel","Very likely. Lord Rod fell in love with her at first sight,\nso did Amaryllis... Oh my god——!","","1","","sorel_m_365"]},{"eOrder":18,"vsParam":["","Sorel","Aren't they two of a kind?\nIt's so romantic and amazing. I'm so excited!","","1","","sorel_m_366"]},{"eOrder":20,"vsParam":["It's true love!","Sorel is so odd..."]},{"eOrder":21,"vsParam":["1"]},{"eOrder":8,"vsParam":["1"]},{"eOrder":98,"vsParam":["hero_m_199","heroine_m_198","1"]},{"eOrder":18,"vsParam":["","Sorel","Yeah! It's like the pure and true love in novels, not\nodd at all! Hehe, I'm even keener to help them!","","1","","sorel_m_367"]},{"eOrder":21,"vsParam":["2"]},{"eOrder":8,"vsParam":["1"]},{"eOrder":98,"vsParam":["hero_m_200","heroine_m_199","1"]},{"eOrder":18,"vsParam":["","Sorel","It's not odd at all! The true love between them is so rare!\nI'm even keener to help them!","","1","","sorel_m_368"]},{"eOrder":22,"vsParam":[]},{"eOrder":8,"vsParam":["1"]},{"eOrder":95,"vsParam":["92"]},{"eOrder":18,"vsParam":["5","Cresson","Here is the thing, Amaryllis. The one who fell in love\nwith you at first sight wants to see you now.","0","","","cresson_m_179"]},{"eOrder":18,"vsParam":["3002","Amaryllis","!\nYou mean... \"that handsome man\"!?","1","","1","amariris_m_007"]},{"eOrder":18,"vsParam":["4","Anise Hyssop","Maybe.\nSo would you like to see him again?","1","","","anis_m_245"]},{"eOrder":18,"vsParam":["3002","Amaryllis","Yeah, sure!\nI'll be expecting you on the \"Kanaris Coast\"!","1","","","amariris_m_008"]},{"eOrder":18,"vsParam":["3002","Amaryllis","Hee hee. I go out a lot to search for \"that\nhandsome man\", so I'm very familiar with Eruleum!","0","","3","amariris_m_009"]},{"eOrder":18,"vsParam":["1010","Peppermint","I see. Be patient.\nWe'll inform Rod right now!","0","","","peppermint_m_368"]},{"eOrder":18,"vsParam":["3002","Amaryllis","Ah, in any minute...\nI'll meet that man once again!","1","","","amariris_m_010"]},{"eOrder":18,"vsParam":["3002","Amaryllis","Wait for me, \"that handsome man\"!\nI'll go find you!","1","","4","amariris_m_011"]},{"eOrder":8,"vsParam":["1"]},{"eOrder":4,"vsParam":["-1"]},{"eOrder":95,"vsParam":["0"]}]}
