{"m_GameObject":{"m_FileID":0,"m_PathID":0},"m_Enabled":1,"m_Script":{"m_FileID":0,"m_PathID":6520365622649918000},"m_Name":"MQ_22_010","vOrderList":[{"eOrder":18,"vsParam":["1010","Peppermint","St Jones Wort Sensei! Bergamot Sensei!\nHehe, listen to me, listen to me!","0","","1"]},{"eOrder":18,"vsParam":["1010","Peppermint","[px]!\nYou've mastered all the four elements of alchemy!","1","","3"]},{"eOrder":18,"vsParam":["1001","St Jones Wort","Oh! You've mastered four elements of alchemy\nwhen you're this young...","0","","1"]},{"eOrder":18,"vsParam":["1001","St Jones Wort","Hehe, you remind me of Bergamot when she was young.\nYou mastered four elements of alchemy as a student too.","0"]},{"eOrder":18,"vsParam":["1002","Bergamot","Indeed...\nBut I'm not aspirant as [px].","1"]},{"eOrder":18,"vsParam":["1002","Bergamot","After all, [px] decides to synthesize\nthe \"Pyroxene of Wisdom\"!","0"]},{"eOrder":18,"vsParam":["1001","St Jones Wort","Haha, indeed.\n[px] deserves to be my favorite student!","0"]},{"eOrder":18,"vsParam":["1001","St Jones Wort","You will make the \"Pyroxene of Wisdom\" someday.\n... I'm so looking forward to it.","0"]},{"eOrder":8,"vsParam":["1"]},{"eOrder":6,"vsParam":["46","0"]},{"eOrder":3,"vsParam":["1"]},{"eOrder":6,"vsParam":["46","0"]},{"eOrder":3,"vsParam":["1"]},{"eOrder":6,"vsParam":["46","0"]},{"eOrder":3,"vsParam":["1"]},{"eOrder":6,"vsParam":["46","0"]},{"eOrder":3,"vsParam":["1"]},{"eOrder":6,"vsParam":["46","0"]},{"eOrder":18,"vsParam":["1010","Peppermint","Wonderful!\nIt seems St Jones Wort Sensei is expecting it!","1","","3"]},{"eOrder":18,"vsParam":["1010","Peppermint","Hey... What about you, Bergamot Sensei?\nAren't you going to commend [px]?","0","","2"]},{"eOrder":18,"vsParam":["1002","Bergamot","Hump, I'm looking forward to it too...\nBut no need to commend.","0"]},{"eOrder":18,"vsParam":["1002","Bergamot","After all, mastering four elements of alchemy is only the\nbasic requirement of synthesizing the \"Pyroxene of Wisdom\".","2"]},{"eOrder":18,"vsParam":["1002","Bergamot","Plus, you haven't figured out the recipe yet.\nKeep trying and don't slacken off.","0"]},{"eOrder":18,"vsParam":["1010","Peppermint","Ah—— Bergamot Sensei is so strict.\n[px], you think so?","4"]},{"eOrder":20,"vsParam":["No, I'll try harder!"]},{"eOrder":21,"vsParam":["1"]},{"eOrder":8,"vsParam":["1"]},{"eOrder":98,"vsParam":["hero_m_213","heroine_m_212","1"]},{"eOrder":18,"vsParam":["1002","Bergamot","...","0"]},{"eOrder":8,"vsParam":["1"]},{"eOrder":1,"vsParam":["0","","2","0"]},{"eOrder":95,"vsParam":["4"]},{"eOrder":3,"vsParam":["1"]},{"eOrder":1,"vsParam":["1","","1","0"]},{"eOrder":18,"vsParam":["","???","Senpai, you haven't gone back yet?\nIt's very late.","","1"]},{"eOrder":18,"vsParam":["","???","Yeah. I'm not as competent as others.\nSo I have to try harder to catch up with them——","","1"]},{"eOrder":8,"vsParam":["1"]},{"eOrder":1,"vsParam":["0","","2","0"]},{"eOrder":95,"vsParam":["0"]},{"eOrder":3,"vsParam":["1"]},{"eOrder":1,"vsParam":["1","","1","0"]},{"eOrder":18,"vsParam":["1002","Bergamot","... Hehe.","0"]},{"eOrder":18,"vsParam":["1010","Peppermint","Wow, Bergamot Sensei, you're smiling!\nIt's creepy! What's going on!?","3","","6"]},{"eOrder":18,"vsParam":["1002","Bergamot","What? I'm creepy!?\nIt's just a smile...!","2","","1"]},{"eOrder":8,"vsParam":["1"]},{"eOrder":1,"vsParam":["0","","2","0"]},{"eOrder":3,"vsParam":["1"]},{"eOrder":1,"vsParam":["1","","1","0"]},{"eOrder":18,"vsParam":["3016","Wistyria","Um...\n[px], you work so hard...","0"]},{"eOrder":18,"vsParam":["3016","Wistyria","Sigh——\nIf only I could help you a bit...","4","","7"]},{"eOrder":18,"vsParam":["2004","Bill Berry","Excuse me, are you a student?\nI need to see [px] for something...","0","","2"]},{"eOrder":18,"vsParam":["3016","Wistyria","Huh? Ah, yes, I'm junior to [px].\nWhat can I do for you?","1","","1"]},{"eOrder":18,"vsParam":["2004","Bill Berry","Oh, great.\nCould you please take a message for me...","0"]},{"eOrder":18,"vsParam":["5","Cresson","... Huh? Wistyria?\nWhat is she and Bill Berry talking about...?","0","","2"]},{"eOrder":8,"vsParam":["1"]}]}
