{"m_GameObject":{"m_FileID":0,"m_PathID":0},"m_Enabled":1,"m_Script":{"m_FileID":0,"m_PathID":6520365622649918000},"m_Name":"SQ_03_030","vOrderList":[{"eOrder":92,"vsParam":["0"]},{"eOrder":1,"vsParam":["0"]},{"eOrder":89,"vsParam":["0"]},{"eOrder":59,"vsParam":["1","-1","1","-1.5","0","-10.75","0"]},{"eOrder":59,"vsParam":["1","-3","3","-0.5","0","-9.75","0"]},{"eOrder":66,"vsParam":["-1","2","-3"]},{"eOrder":66,"vsParam":["-3","2","-1"]},{"eOrder":94,"vsParam":["2","-1"]},{"eOrder":1,"vsParam":["1"]},{"eOrder":92,"vsParam":["1"]},{"eOrder":69,"vsParam":["-3","8","1","0"]},{"eOrder":18,"vsParam":["3","Sorel","Phew... Thank you, [px].\nI'm saved...","3","","","sorel_m_033"]},{"eOrder":18,"vsParam":["1010","Peppermint","Uh, you're welcome...\nSorel, why did the monster chase after you?","0","","2","peppermint_m_068"]},{"eOrder":18,"vsParam":["1010","Peppermint","You said \"whoever takes down the monster\nfirst wins!\" and then rushed out.","0","","1","peppermint_m_069"]},{"eOrder":69,"vsParam":["-3","9","1","0"]},{"eOrder":18,"vsParam":["3","Sorel","Um... That's because I accidentally stepped onto\nthe monster's tail while searching for it.","3","","","sorel_m_034"]},{"eOrder":18,"vsParam":["3","Sorel","So I pissed it off...\nI couldn't defeat it, so it chased after me...","3","","","sorel_m_035"]},{"eOrder":18,"vsParam":["1010","Peppermint","I see. Hee hee, Jesus...\nSorel, you were too careless!","1","","","peppermint_m_070"]},{"eOrder":69,"vsParam":["-3","9","1","0"]},{"eOrder":18,"vsParam":["3","Sorel","Hmm...\nYou got me... Ouch!","4","","","sorel_m_036"]},{"eOrder":18,"vsParam":["1010","Peppermint","What's wrong... Oh, you're wounded!","3","","1","peppermint_m_071"]},{"eOrder":69,"vsParam":["-3","5","1","0"]},{"eOrder":18,"vsParam":["3","Sorel","Ah, you got a bruise, but it's not serious.\nIt will heal even without any treatment.","4","","","sorel_m_037"]},{"eOrder":23,"vsParam":["1"]},{"eOrder":20,"vsParam":["No, we'd better treat it.","No need to grit your teeth against the pain!"]},{"eOrder":21,"vsParam":["1"]},{"eOrder":8,"vsParam":["1"]},{"eOrder":69,"vsParam":["-1","5","1","0"]},{"eOrder":98,"vsParam":["hero_m_019","","1"]},{"eOrder":21,"vsParam":["2"]},{"eOrder":8,"vsParam":["1"]},{"eOrder":69,"vsParam":["-1","11","1","0"]},{"eOrder":98,"vsParam":["hero_m_020","","1"]},{"eOrder":22,"vsParam":[]},{"eOrder":26,"vsParam":[]},{"eOrder":20,"vsParam":["No, we'd better treat it.","No need to grit your teeth against the pain!"]},{"eOrder":21,"vsParam":["1"]},{"eOrder":8,"vsParam":["1"]},{"eOrder":69,"vsParam":["-1","5","1","0"]},{"eOrder":98,"vsParam":["","heroine_m_019","1"]},{"eOrder":21,"vsParam":["2"]},{"eOrder":8,"vsParam":["1"]},{"eOrder":69,"vsParam":["-1","5","1","0"]},{"eOrder":98,"vsParam":["","heroine_m_020","1"]},{"eOrder":22,"vsParam":[]},{"eOrder":27,"vsParam":[]},{"eOrder":18,"vsParam":["1010","Peppermint","Oh, right!\n[px] could make medicine for you!","0","","1","peppermint_m_072"]},{"eOrder":69,"vsParam":["-3","6","1","0"]},{"eOrder":18,"vsParam":["3","Sorel","Um...\nIt does hurt, so I guess I have to seek help...","3","","","sorel_m_038"]},{"eOrder":18,"vsParam":["1010","Peppermint","Hee hee, just show Sorel how powerful alchemy is!","1","","3","peppermint_m_073"]},{"eOrder":69,"vsParam":["-3","9","1","0"]},{"eOrder":18,"vsParam":["3","Sorel","Ah, that's what you want! But whatever.\nSorry, [px]. Please make specific medicine for me.","3","","","sorel_m_039"]},{"eOrder":8,"vsParam":["1"]},{"eOrder":1,"vsParam":["0"]},{"eOrder":59,"vsParam":["0","-1"]},{"eOrder":59,"vsParam":["0","-3"]},{"eOrder":89,"vsParam":["1"]},{"eOrder":1,"vsParam":["1"]}]}
