{"m_GameObject":{"m_FileID":0,"m_PathID":0},"m_Enabled":1,"m_Script":{"m_FileID":0,"m_PathID":6520365622649918000},"m_Name":"CQ_ANN_007_030","vOrderList":[{"eOrder":92,"vsParam":["0"]},{"eOrder":1,"vsParam":["0"]},{"eOrder":97,"vsParam":["0"]},{"eOrder":89,"vsParam":["0"]},{"eOrder":59,"vsParam":["1","-1","1","27.5","0.02","-16.5","0"]},{"eOrder":59,"vsParam":["1","-3","3","28.5","0.02","-17","0"]},{"eOrder":59,"vsParam":["1","-4","4","26.5","0.02","-17.5","0"]},{"eOrder":59,"vsParam":["1","-5","5","27","0.02","-15","0"]},{"eOrder":59,"vsParam":["1","-6","6","28.25","0.02","-15.5","0"]},{"eOrder":59,"vsParam":["1","-1022","1022","29.375","0.02","-17.25","150"]},{"eOrder":66,"vsParam":["-1","2","-1022","0"]},{"eOrder":66,"vsParam":["-3","2","-1022","0"]},{"eOrder":66,"vsParam":["-4","2","-1022","0"]},{"eOrder":66,"vsParam":["-5","2","-1022","0"]},{"eOrder":66,"vsParam":["-6","2","-1022","0"]},{"eOrder":94,"vsParam":["2","-1"]},{"eOrder":1,"vsParam":["1"]},{"eOrder":92,"vsParam":["1"]},{"eOrder":48,"vsParam":["202","ローズヒップ邸"]},{"eOrder":18,"vsParam":["6","アンゼリカ","ネトル","0"]},{"eOrder":18,"vsParam":["1022","ネトル","……","0"]},{"eOrder":18,"vsParam":["6","アンゼリカ","ごめんね、来るのが遅くなっちゃって。\r\nそれに……今までネトルの気持ちに気付いてあげられなくて","4"]},{"eOrder":18,"vsParam":["1022","ネトル","……","0"]},{"eOrder":18,"vsParam":["6","アンゼリカ","ネトルが強くなろうって頑張るのは、すごく嬉しい。\r\nうちもずっと、ネトルにそうなってほしいって思ってた","0"]},{"eOrder":18,"vsParam":["6","アンゼリカ","ううん、思ってた『つもり』だった。\r\nけど、いつの間にかネトルの体のことばかり気にしてた","3"]},{"eOrder":18,"vsParam":["6","アンゼリカ","ネトルの気持ちなんて考えずに、\r\nただネトルは自分が守らなきゃって、そればっかり……","3"]},{"eOrder":18,"vsParam":["6","アンゼリカ","ごめんね……ネトル。\r\nうち、ダメなお姉ちゃんで……","4"]},{"eOrder":66,"vsParam":["-1022","2","-6","0"]},{"eOrder":18,"vsParam":["1022","ネトル","……っ！\r\n違うよ……。お姉ちゃんは悪くない","0"]},{"eOrder":18,"vsParam":["1022","ネトル","お姉ちゃんはいつも、ぼくのことを一番に考えてくれてた。\r\nなのに、ぼくはお姉ちゃんにひどいことを……","0"]},{"eOrder":18,"vsParam":["1022","ネトル","ぼくが強くなりたかった一番の理由は……。\r\nお姉ちゃんを守りたかったからなのに……。それなのに……","0"]},{"eOrder":18,"vsParam":["1022","ネトル","ぼくは、お姉ちゃんを傷つけて……。\r\nごめんね……ごめんね、お姉ちゃん……！","0"]},{"eOrder":18,"vsParam":["6","アンゼリカ","いいんだよ……。いいんだよ、ネトル……。\r\nだって、うちたちは……姉弟なんだから……！","3"]},{"eOrder":18,"vsParam":["1022","ネトル","うん……！　ぐすっ……！\r\nお姉ちゃん……！　お姉ちゃぁぁん……！","0"]},{"eOrder":1,"vsParam":["0"]},{"eOrder":8,"vsParam":["1"]},{"eOrder":1,"vsParam":["1"]},{"eOrder":18,"vsParam":["1022","ネトル","うう……ずびっ。\r\nみんなに泣いてるところ、見られちゃった……","0"]},{"eOrder":18,"vsParam":["3","ソレル","あはは、気にしない気にしない。\r\n子供のうちは、思いっきり泣いたって誰も気にしないわよ","1"]},{"eOrder":18,"vsParam":["4","アニスヒソップ","そうですよ。ネトルくん。たまには、自分の気持ちを\r\n素直にぶつけることも大切なんですからね？","1"]},{"eOrder":18,"vsParam":["1022","ネトル","うん……","1"]},{"eOrder":18,"vsParam":["1010","ペパーミント","あっ、そうだ。\r\nねぇねぇ、アンゼリカ。あれ……","1"]},{"eOrder":18,"vsParam":["6","アンゼリカ","うん。\r\n実はね？　ネトルに渡したいものがあるの","1"]},{"eOrder":8,"vsParam":["1"]},{"eOrder":6,"vsParam":["71","1"]},{"eOrder":18,"vsParam":["1022","ネトル","え……。\r\nこれって……お守り？","0"]},{"eOrder":18,"vsParam":["6","アンゼリカ","うん、うちらの故郷のお守りだよ。\r\nこのお守りには、うちとみんなの想いがこもってる","1"]},{"eOrder":18,"vsParam":["6","アンゼリカ","ネトルがいつか、誰かを……。ネトルが守りたいみんなを\r\n守れるくらい、強くなれますようにって","1"]},{"eOrder":18,"vsParam":["1022","ネトル","そう、なんだ……。\r\nねぇ、[px]さん。ぼく、なれるかな……","0"]},{"eOrder":18,"vsParam":["1022","ネトル","お姉ちゃんを……。\r\nみんなを守れるくらい、強く……！","0"]},{"eOrder":23,"vsParam":["1"]},{"eOrder":20,"vsParam":["「きっとなれるよ」","「ぼくの一歩手前くらいまでは？」"]},{"eOrder":21,"vsParam":["1"]},{"eOrder":18,"vsParam":["1022","ネトル","うん……うんっ！　ぼく、絶対に強くなるよ！\r\nだから……見ててね、みんな！！","1"]},{"eOrder":21,"vsParam":["2"]},{"eOrder":18,"vsParam":["1010","ペパーミント","いやー、別に[px]って腕っ節強くないし？\r\nだから……きっとなれるよ、ネトル！","3"]},{"eOrder":18,"vsParam":["1022","ネトル","うん……うんっ！　ぼく、絶対に強くなるよ！\r\nだから……見ててね、みんな！！","1"]},{"eOrder":22,"vsParam":[]},{"eOrder":26,"vsParam":[]},{"eOrder":20,"vsParam":["「きっとなれるよ」","「わたしの一歩手前くらいまでは？」"]},{"eOrder":21,"vsParam":["1"]},{"eOrder":18,"vsParam":["1022","ネトル","うん……うんっ！　ぼく、絶対に強くなるよ！\r\nだから……見ててね、みんな！！","1"]},{"eOrder":21,"vsParam":["2"]},{"eOrder":18,"vsParam":["1010","ペパーミント","いやー、別に[px]って腕っ節強くないし？\r\nだから……きっとなれるよ、ネトル！","3"]},{"eOrder":18,"vsParam":["1022","ネトル","うん……うんっ！　ぼく、絶対に強くなるよ！\r\nだから……見ててね、みんな！！","1"]},{"eOrder":22,"vsParam":[]},{"eOrder":27,"vsParam":[]},{"eOrder":8,"vsParam":["1"]},{"eOrder":49,"vsParam":[]},{"eOrder":92,"vsParam":["0"]},{"eOrder":1,"vsParam":["0"]},{"eOrder":59,"vsParam":["0","-1"]},{"eOrder":59,"vsParam":["0","-3"]},{"eOrder":59,"vsParam":["0","-4"]},{"eOrder":59,"vsParam":["0","-5"]},{"eOrder":59,"vsParam":["0","-6"]},{"eOrder":59,"vsParam":["0","-1022"]},{"eOrder":97,"vsParam":["1"]},{"eOrder":89,"vsParam":["1"]},{"eOrder":1,"vsParam":["1"]}]}
