{"m_GameObject":{"m_FileID":0,"m_PathID":0},"m_Enabled":1,"m_Script":{"m_FileID":0,"m_PathID":6520365622649918000},"m_Name":"CQ_SOP_006_020","vOrderList":[{"eOrder":18,"vsParam":["1010","ペパーミント","ソフィー、お待たせ！\n頼まれてたもの、持ってきたよー！","1"]},{"eOrder":18,"vsParam":["5014","ソフィー","ありがとう！　よーし、これで全部揃った～！\nじゃあ早速、錬金釜を作ってみるね！","1","","3"]},{"eOrder":18,"vsParam":["5014","ソフィー","材料はこの順番で入れて……。\nゆっくり混ぜて……","0"]},{"eOrder":18,"vsParam":["3","ソレル","ほ、ホントに釜で釜を作ってる……。\nこんなこともできるのね……","4"]},{"eOrder":18,"vsParam":["5","クレソン","今更言うのもなんだけどさ。\n錬金術って、本当に不思議だよなあ……","4"]},{"eOrder":18,"vsParam":["5014","ソフィー","よし、でっきた～！","1"]},{"eOrder":18,"vsParam":["1010","ペパーミント","おおっ！　錬金釜が増え……てない！？\nえ、どういうこと！？","4","","7"]},{"eOrder":18,"vsParam":["3","ソレル","錬金釜で錬金釜を作ったのよね！？\nできた錬金釜はどこに行ったの！？","2","","1"]},{"eOrder":18,"vsParam":["5014","ソフィー","へ、ここにあるじゃない。\nこれだよ、これ","0","","2"]},{"eOrder":18,"vsParam":["4","アニスヒソップ","いや、それは元の釜なのでは……？","4","","6"]},{"eOrder":18,"vsParam":["5014","ソフィー","違うよ～、これが新しい釜！\nほら、こことか……性能がぜんぜん違うでしょ？","0"]},{"eOrder":18,"vsParam":["5","クレソン","まったくわからん……！\nそれに、これが新しい釜なら、今までの釜はどこに……！？","4"]},{"eOrder":18,"vsParam":["3","ソレル","ふ、深く考えるのはやめておいた方がよさそうね！\nええ、やめておきましょ！","4","","7"]},{"eOrder":18,"vsParam":["4","アニスヒソップ","そ、そうですね……。\nともあれお疲れ様です、ソフィーさん","0"]},{"eOrder":18,"vsParam":["4","アニスヒソップ","ところで……ソフィーさんの世界では、\n錬金釜の調合は珍しくないことなのですか？","0"]},{"eOrder":18,"vsParam":["5014","ソフィー","んー、どうなんだろ。\nそもそも、あたし以外の錬金術士をあんまり知らなくて","4","","2"]},{"eOrder":18,"vsParam":["5014","ソフィー","ただおばあちゃんはちょこちょこ釜を作ってた……\nような気がする！","0"]},{"eOrder":18,"vsParam":["3","ソレル","なるほど……。まぁ、使う道具を自分好みに改良するのは\n理に適ってはいるわよね","0"]},{"eOrder":18,"vsParam":["3","ソレル","ふふー。錬金術科でも錬金釜の研究をしたら、\n面白い発見があるかもしれないわよ？","1"]},{"eOrder":18,"vsParam":["1010","ペパーミント","あははー。さすがのベルガモットせんせーも\n釜で釜を作るって言ったらびっくりしそうだけどねー","1"]},{"eOrder":18,"vsParam":["4","アニスヒソップ","ふふっ、ですね……。\n世界が違えば、錬金釜を作ってしまうこともある、と","0"]},{"eOrder":18,"vsParam":["4","アニスヒソップ","錬金術は本当に、奥が深いです……！","1"]},{"eOrder":8,"vsParam":["1"]}]}
