{"m_GameObject":{"m_FileID":0,"m_PathID":0},"m_Enabled":1,"m_Script":{"m_FileID":0,"m_PathID":6520365622649918000},"m_Name":"EV_050_006_010","vOrderList":[{"eOrder":18,"vsParam":["1010","ペパーミント","オーゼイユ。\nセキチクさんの花火、だいぶ取り返したけど……どう？","4"]},{"eOrder":18,"vsParam":["5025","オーゼイユ","んー。セキチクさんから聞き取った感じだと、\n確かにだいたい取り返せたみたい","0"]},{"eOrder":18,"vsParam":["5025","オーゼイユ","でも……一番ヤバいのがまだ残ってるのよね","4"]},{"eOrder":18,"vsParam":["5010","アーシャ","一番……ヤバいの？","4"]},{"eOrder":18,"vsParam":["5025","オーゼイユ","ええ……。\nセキチクさんの一番の自信作、その名も――","0"]},{"eOrder":18,"vsParam":["5025","オーゼイユ","三尺玉『大輪ギャラクシア』……！","2"]},{"eOrder":18,"vsParam":["5001","ロロナ","『大輪ギャラクシア』ー！？\nえっ、なにその名前だけでもすごそうなの……！？","4"]},{"eOrder":18,"vsParam":["5026","フォニク","しかも三尺玉って！\nもし市街地で暴発しようものなら……！","4"]},{"eOrder":18,"vsParam":["5025","オーゼイユ","ええ、大変なことになるわ。\nだから、絶対に放っておくわけにはいかない","0"]},{"eOrder":18,"vsParam":["5014","ソフィー","だね。なんとかして探し出さないと……！","0"]},{"eOrder":18,"vsParam":["1010","ペパーミント","でもさぁ、手がかりがぜんぜんなくない？","4"]},{"eOrder":18,"vsParam":["5002","マリー","ちっこいのと、中くらいのと、飛んでるの……。\nセキチクさんが言ってた魔物は全部こらしめたよね？","4"]},{"eOrder":18,"vsParam":["5010","アーシャ","まさか……。\n他に、魔物たちの親玉がいる……？","4"]},{"eOrder":18,"vsParam":["5025","オーゼイユ","アーシャ、あたしも同じことを思ったの。\nそれでね、考えてみたんだけど……","0"]},{"eOrder":18,"vsParam":["5025","オーゼイユ","白蓮池で戦った魔物のこと、覚えてる？\nソフィーの爆弾を食べた、あの魔物よ","0"]},{"eOrder":18,"vsParam":["5014","ソフィー","ああ。あの魔物がどうか……あっ！","0"]},{"eOrder":18,"vsParam":["5025","オーゼイユ","そう。魔物たちが、\n花火を『食べる』ために盗んだんだとしたら……？","0"]},{"eOrder":18,"vsParam":["5025","オーゼイユ","そして、あの魔物と同じく、\n火薬を食べる魔物がまだいるんだとしたら……？","0"]},{"eOrder":18,"vsParam":["5001","ロロナ","白蓮池に行ってみるべき……ってこと、ですか？","0"]},{"eOrder":18,"vsParam":["5025","オーゼイユ","その通り。\n手がかりがない今、試してみる価値はあると思うの","0"]},{"eOrder":18,"vsParam":["5026","フォニク","そうですね、私も賛成です。\n実は一人で白蓮池を調査しに行ったのですが……","0"]},{"eOrder":18,"vsParam":["5026","フォニク","あの魔物と似た足跡が散見されました。\n火薬の材料となる鉱石が食された跡もありましたし……","0"]},{"eOrder":18,"vsParam":["5026","フォニク","白蓮池付近に、火薬を主食とする魔物がまだいるのは、\nほぼ確実だと考えます","0"]},{"eOrder":18,"vsParam":["5002","マリー","なるほど、じゃあやることは決まったね。\n白蓮池に行って……","2"]},{"eOrder":18,"vsParam":["5010","アーシャ","『大輪ギャラクシア』を取り戻す！\n……ですね！","2"]},{"eOrder":18,"vsParam":["5014","ソフィー","うん、それじゃあ……！\nペパーミントちゃん、どうぞ♪","1"]},{"eOrder":18,"vsParam":["1010","ペパーミント","ええっ！？　……こほん。\n『でっかい花火を取り戻そう作戦』！　発動だ～！","2"]},{"eOrder":18,"vsParam":["","みんな","おーっ！！","0","1"]},{"eOrder":18,"vsParam":["1010","ペパーミント","うー、わかんない……。\nソフィーの緩急がわかんないよぉ……","4"]},{"eOrder":8,"vsParam":["1"]}]}
