{"m_GameObject":{"m_FileID":0,"m_PathID":0},"m_Enabled":1,"m_Script":{"m_FileID":0,"m_PathID":6520365622649918000},"m_Name":"EV_DRA_005_010","vOrderList":[{"eOrder":18,"vsParam":["1004","ルー","ふむ……君たちが拾ったドラゴンのウロコだが、\nどうやらこれ一枚でも破格の魔力を秘めているようだ","0"]},{"eOrder":18,"vsParam":["4","アニスヒソップ","やはり、そうですか……。落ちただけで\n時空のゆがみが生まれるほどでしたからね……","4"]},{"eOrder":18,"vsParam":["1010","ペパーミント","ね、ねえ、それってさ……本体は\nもっともーっと強い魔力を持ってるってことだよね？","3","","2"]},{"eOrder":20,"vsParam":["「諦めよっか……」","「きっとなんとかなる！」"]},{"eOrder":21,"vsParam":["1"]},{"eOrder":8,"vsParam":["1"]},{"eOrder":98,"vsParam":["","","1"]},{"eOrder":18,"vsParam":["5008","ミミ","ちょっと、なに言ってるのよ！\n私が言ったことももう忘れたってわけ？","2","","1"]},{"eOrder":18,"vsParam":["1010","ペパーミント","そ、そんなことないよっ！　[px]のことだし、\n場を和ませようとして、ねっ！　ねー！？","1"]},{"eOrder":18,"vsParam":["4","アニスヒソップ","きっと、ドラゴンを倒す方法はありますよ。\nみんなで考えてみれば、なにか思い浮かぶかもしれません","0"]},{"eOrder":21,"vsParam":["2"]},{"eOrder":8,"vsParam":["1"]},{"eOrder":98,"vsParam":["","","1"]},{"eOrder":18,"vsParam":["5008","ミミ","ええ、そうね。『きっと』じゃなくて\n『必ず』って言うべきところだけれど","1"]},{"eOrder":18,"vsParam":["1010","ペパーミント","うん！　ドラゴンを倒す方法、\nみんなで考えてみよう！","1","","3"]},{"eOrder":22,"vsParam":[]},{"eOrder":18,"vsParam":["1004","ルー","あのドラゴンと戦うにあたって……\nやはり、厄介なのはあの強大な魔力だね","3"]},{"eOrder":18,"vsParam":["1004","ルー","[px]の道具が通じなかったのも、\n魔力に守られて届かなかったからだろう","0"]},{"eOrder":18,"vsParam":["1010","ペパーミント","それに、時空のゆがみまで作っちゃうもんね。\nそこから魔物も出てくるし……","3"]},{"eOrder":18,"vsParam":["3","ソレル","ドラゴンと他の魔物を同時に……なんて、\nさすがにやってられないわよ","3","","6"]},{"eOrder":18,"vsParam":["5005","ステルク","ふむ……ドラゴンと戦うにはまず、\nその魔力を封じる必要がある、というわけだな","0"]},{"eOrder":18,"vsParam":["3","ソレル","うーん……。そんな方法、あるのかしら……","4","","7"]},{"eOrder":18,"vsParam":["1010","ペパーミント","……あ！　魔力とか魔法のことなら、\n妖精王様がなにか知ってるかも！","1","","1"]},{"eOrder":18,"vsParam":["5005","ステルク","妖精王……？\nああ、そうか。君も妖精……","0","","2"]},{"eOrder":18,"vsParam":["5005","ステルク","……ええと。\n妖精、ということでいいのか？","3","","7"]},{"eOrder":18,"vsParam":["1010","ペパーミント","妖精だよっ！\nほら、この羽根がなによりの証拠っ！","2","","5"]},{"eOrder":18,"vsParam":["4","アニスヒソップ","あはは……。それはともかく、\nツンベルギア様に聞けば、なにかわかるかもしれませんね","1"]},{"eOrder":18,"vsParam":["3","ソレル","ええ。バカ妖精が本当に妖精かどうかはほっといて、\n妖精郷に行ってみましょ！","1"]},{"eOrder":18,"vsParam":["1010","ペパーミント","だから妖精だってばー！　アタシがいないと\n妖精王様にも会えないんだからね！　そこわかってる！？","2","","5"]},{"eOrder":18,"vsParam":["5008","ミミ","はいはい、わかったから行くわよ。\nもう少し緊張感を持ちなさいよね、あなたたち……","4"]},{"eOrder":8,"vsParam":["1"]}]}
