{"m_GameObject":{"m_FileID":0,"m_PathID":0},"m_Enabled":1,"m_Script":{"m_FileID":0,"m_PathID":6520365622649918000},"m_Name":"CQ_ROR_007_010","vOrderList":[{"eOrder":48,"vsParam":["10","アカデミー中庭"]},{"eOrder":18,"vsParam":["","学生Ａ","ロロナちゃーん！　プレーンパイひとつー！","","1","","mob_l_003"]},{"eOrder":18,"vsParam":["","学生Ｂ","こっちはハチミツパイをくれー！\r\nあ、バターたっぷりで頼む！","","1","","mob_l_004"]},{"eOrder":18,"vsParam":["5001","ロロナ","わ、わぁ、押さないで！\r\nパイならたくさんありますから……！","4","","6","rorona_l_065"]},{"eOrder":8,"vsParam":["1"]},{"eOrder":1,"vsParam":["0"]},{"eOrder":3,"vsParam":["1"]},{"eOrder":1,"vsParam":["1"]},{"eOrder":18,"vsParam":["5001","ロロナ","ふぅ……","3","","","rorona_l_066"]},{"eOrder":18,"vsParam":["3","ソレル","あはは、忙しそうね、ロロナ","1","","","sorel_l_026"]},{"eOrder":18,"vsParam":["5001","ロロナ","あ、はい……。思いつきで始めたパイ屋さんが、\r\nおかげさまで大盛況で……","0","","","rorona_l_067"]},{"eOrder":18,"vsParam":["1010","ペパーミント","そりゃそうだよ。だってロロナのパイ、最高だもん！\r\n一回食べたら病みつきになっちゃうくらい！","1","","3","peppermint_l_019"]},{"eOrder":18,"vsParam":["4","アニスヒソップ","そうですね。ロロナさんのパイは、\r\n至高の甘味と言ってもいいくらいですから","2","","","anis_l_021"]},{"eOrder":18,"vsParam":["4","アニスヒソップ","でも、大丈夫ですか？\r\n忙しくて、ゆっくり休めていないのでは？","1","","2","anis_l_022"]},{"eOrder":18,"vsParam":["5001","ロロナ","それは大丈夫なんですけど……。\r\n実はちょっと悩んでることがあって……","4","","7","rorona_l_068"]},{"eOrder":20,"vsParam":["「屋台の経営がうまくいってないとか？」","「また新作のレシピを閃いたとか！」"]},{"eOrder":21,"vsParam":["1"]},{"eOrder":8,"vsParam":["1"]},{"eOrder":98,"vsParam":["hero_l_019","heroine_l_019","1"]},{"eOrder":18,"vsParam":["5001","ロロナ","いえ。また新作のパイのレシピを思いついたんですけど、\r\n材料を採りに行く時間がないんです","4","","6","rorona_l_069"]},{"eOrder":21,"vsParam":["2"]},{"eOrder":8,"vsParam":["1"]},{"eOrder":98,"vsParam":["hero_l_020","heroine_l_020","1"]},{"eOrder":18,"vsParam":["5001","ロロナ","あ、そうなんです。\r\nでも、忙しくて材料を採りに行く時間がなくて……","3","","6","rorona_l_070"]},{"eOrder":22,"vsParam":[]},{"eOrder":18,"vsParam":["3","ソレル","なるほどね。そういうことならあたしたちを頼りなさい。\r\nだってあたしたち、友達でしょ？","1","","","sorel_l_027"]},{"eOrder":18,"vsParam":["5001","ロロナ","……！　友達……！\r\nそっか、友達……！","0","","1","rorona_l_071"]},{"eOrder":18,"vsParam":["4","アニスヒソップ","ええ。私もソレルも、[px]さんも。\r\nロロナさんが困っていたら、いつでも手を貸します","1","","","anis_l_023"]},{"eOrder":18,"vsParam":["1010","ペパーミント","もちろんアタシもね！　それで、ロロナ。\r\n今度はどんな材料が欲しいの？","1","","1","peppermint_l_020"]},{"eOrder":18,"vsParam":["5001","ロロナ","あ、えっと。今度は宝石でパイを作りたくて。\r\nだから、なるべく美味しそうな宝石を持ってきてください！","1","","3","rorona_l_072"]},{"eOrder":18,"vsParam":["","全員","宝……石ぃっ！？","","1"]},{"eOrder":8,"vsParam":["1"]},{"eOrder":49,"vsParam":[]}]}
