{"m_GameObject":{"m_FileID":0,"m_PathID":0},"m_Enabled":1,"m_Script":{"m_FileID":0,"m_PathID":6520365622649918000},"m_Name":"EV_09_001_010","vOrderList":[{"eOrder":18,"vsParam":["5010","アーシャ","あ！ こ、こんにちは。\nわたし、アーシャ・アルトゥールっていいます","0"]},{"eOrder":18,"vsParam":["5010","アーシャ","ベルちゃんと一緒に薬の材料を探していたら、\nいつの間にかモヤモヤに巻き込まれちゃって……","3"]},{"eOrder":18,"vsParam":["5010","アーシャ","気が付いたら綺麗な泉の近くにいたんです。\nそれから、ルーさんがここに連れてきてくれて……","0"]},{"eOrder":18,"vsParam":["4","アニスヒソップ","ルー先生が、ですか？","0"]},{"eOrder":18,"vsParam":["1004","ルー","ああ。彼女は、僕ですら聞いたこともないような\n薬草をいくつも知っていてね","0"]},{"eOrder":18,"vsParam":["1004","ルー","もっと詳しい話を聞かせてもらおうと思って\n落ち着いて話せるところへ来てもらった、というわけさ","0"]},{"eOrder":18,"vsParam":["1010","ペパーミント","へぇ、ルーせんせーでも知らない薬草かあー。\nあ！　もしかして、アーシャは別の世界から来たの？","1","","1"]},{"eOrder":18,"vsParam":["5010","アーシャ","うーん……それが、よくわからないんです。\n何が起きたんでしょう……？","4","","7"]},{"eOrder":18,"vsParam":["1004","ルー","おそらく、『時空のゆがみ』に巻き込まれたんだろう。\nここは君のいた世界とは別の世界だと思っていい","0"]},{"eOrder":18,"vsParam":["1004","ルー","このぼくが知らない植物をあれだけ知っているんだ。\n……そうでなければ、説明がつかない","0"]},{"eOrder":18,"vsParam":["1010","ペパーミント","あはは……。\nルーせんせーってば、そこで判断するんだ……","3","","6"]},{"eOrder":18,"vsParam":["5010","アーシャ","別の世界、かあ……。\nうーん、なんだか大変なことになっちゃった","3"]},{"eOrder":18,"vsParam":["5010","アーシャ","ベルちゃんともはぐれちゃったし……。\nきっと大丈夫だとは思うけど……","4"]},{"eOrder":18,"vsParam":["3","ソレル","ベルちゃん？　あ、ひょっとしてあの子のことかしら。\nそれなら心配ないわよ！","0"]},{"eOrder":8,"vsParam":["1"]},{"eOrder":18,"vsParam":["","？？？","あ、いたー！　あの子よ、あたしが探してたの！\nねえ、もう離してー！！","","1"]},{"eOrder":18,"vsParam":["","マジョラム","だめよ、すり傷の手当てをしなくちゃ！\nああ、あんなに火の魔法を使っていたから、火傷も……！","","1"]},{"eOrder":18,"vsParam":["","？？？","あー、もう！　このくらい平気だってば！\nアーシャ、なんとかしてー！","","1"]},{"eOrder":18,"vsParam":["5010","アーシャ","この声は……ベルちゃん！？\nよかった、ベルちゃんもここに来てたんだ！","1","","3"]},{"eOrder":18,"vsParam":["5011","ウィルベル","うー、まあね……。来たっていうか、\n無理やり連れて来られたっていうか……","4"]},{"eOrder":18,"vsParam":["5011","ウィルベル","森で魔物を蹴散らしてたら、あっちにいる\nいろいろとデッカイ女の人に捕まっちゃってさ","2"]},{"eOrder":18,"vsParam":["5011","ウィルベル","魔物から助けるだとか、ケガの手当てだとか……\nもう逃げるのも大変で、そのままここに……","2"]},{"eOrder":18,"vsParam":["3","ソレル","あー……いろいろとデッカイ人、ね……。\n逃げるのが大変って気持ちはちょっとわかるかも……","0","","6"]},{"eOrder":18,"vsParam":["1010","ペパーミント","あはは……。それで、この子が「ベル」ちゃん？\nアーシャとはぐれちゃったっていう……","3"]},{"eOrder":18,"vsParam":["5010","アーシャ","はい、ベルちゃんです！\nすっごく頼りになる魔法使いさんなんですよ","1","","1"]},{"eOrder":18,"vsParam":["5011","ウィルベル","ちょっと、アーシャ！？\nあたしが魔法使いってことは秘密なんだってば！","2","","5"]},{"eOrder":18,"vsParam":["5010","アーシャ","あ……！　ご、ごめんね、ベルちゃん。\nつい……","3"]},{"eOrder":18,"vsParam":["5011","ウィルベル","もー、アーシャってば……。\nま、ばれちゃったからにはしょうがないか","4"]},{"eOrder":18,"vsParam":["5011","ウィルベル","こほん。あたしはウィルベル・フォル＝エルスリート。\n魔法使いだってことは、誰にも言わないように！","1"]},{"eOrder":18,"vsParam":["1010","ペパーミント","あ、隠さなくてもいいと思うよ！\nここは二人がいた世界とは違う世界なんだ","1"]},{"eOrder":18,"vsParam":["5011","ウィルベル","え、なに……？　違う世界？","4","","2"]},{"eOrder":18,"vsParam":["3","ソレル","ええ。ここじゃ魔法使いなんて当たり前だし、\n『いろいろとデッカイ人』も魔法使いの先生よ","0"]},{"eOrder":18,"vsParam":["5011","ウィルベル","そ、そうなの！？　うわぁ、\nとんでもないところに来たのね、あたしたち……","2"]},{"eOrder":18,"vsParam":["5010","アーシャ","ふふ、そうみたいだね。\nでも、きっとすぐ元の世界に帰れると思うよ","1"]},{"eOrder":18,"vsParam":["1004","ルー","いや、それについてだが……\nその方法が見つかるまでは、まだ時間がかかりそうだ","0"]},{"eOrder":18,"vsParam":["5010","アーシャ","え……そうなんですか？　うーん、どうしよう。\nわたし、妹を探さないといけなくて……","3","","7"]},{"eOrder":18,"vsParam":["1004","ルー","とりあえず、しばらくはここで過ごすといいだろう。\n君の妹についても、情報が集まるかもしれない","0"]},{"eOrder":18,"vsParam":["5011","ウィルベル","ま、他に行くあてもないし、そうしよっか。\nこれからよろしくね、あんたたち！","1","","1"]},{"eOrder":18,"vsParam":["1010","ペパーミント","うん！　こちらこそよろしくね、\nアーシャ、ウィルベル！","1"]},{"eOrder":18,"vsParam":["5010","アーシャ","はい！　よろしくお願いします！","1","","3"]},{"eOrder":8,"vsParam":["1"]}]}
