{"m_GameObject":{"m_FileID":0,"m_PathID":0},"m_Enabled":1,"m_Script":{"m_FileID":0,"m_PathID":6520365622649918000},"m_Name":"SQ_SUB_029_020","vOrderList":[{"eOrder":92,"vsParam":["0"]},{"eOrder":1,"vsParam":["0"]},{"eOrder":97,"vsParam":["0"]},{"eOrder":89,"vsParam":["0"]},{"eOrder":59,"vsParam":["1","-1","1","-12","0.02","-22","0"]},{"eOrder":59,"vsParam":["1","-3","3","-11","0.02","-21.25","0"]},{"eOrder":59,"vsParam":["1","-4","4","-13","0.02","-21","0"]},{"eOrder":59,"vsParam":["1","-5","5","-11.5","0.02","-22.5","0"]},{"eOrder":59,"vsParam":["1","-6","6","-13","0.02","-22","0"]},{"eOrder":59,"vsParam":["1","-1019","1019","-12.25","0.02","-20.5","0"]},{"eOrder":66,"vsParam":["-1","2","-1019","0"]},{"eOrder":66,"vsParam":["-3","2","-1019","0"]},{"eOrder":66,"vsParam":["-4","2","-1019","0"]},{"eOrder":66,"vsParam":["-5","2","-1019","0"]},{"eOrder":66,"vsParam":["-6","2","-1019","0"]},{"eOrder":66,"vsParam":["-1019","2","-1","0"]},{"eOrder":94,"vsParam":["2","-1"]},{"eOrder":1,"vsParam":["1"]},{"eOrder":92,"vsParam":["1"]},{"eOrder":18,"vsParam":["1010","ペパーミント","はーい、キャットニップ～♪\r\nあ～ん","1"]},{"eOrder":69,"vsParam":["-1019","9","1","0"]},{"eOrder":18,"vsParam":["1019","キャットニップ","にゃ？　あ～ん……もごっ！\r\nにゃ、にゃ、にゃ～っ！？","0"]},{"eOrder":69,"vsParam":["-1019","0","0","0"]},{"eOrder":69,"vsParam":["-1019","7","1","0"]},{"eOrder":18,"vsParam":["1019","キャットニップ","これは～♪　頼んでた～♪　のど飴にゃ～♪\r\nあたしの喉は～♪　すっかり元通～り～♪　にゃっ♪","0"]},{"eOrder":69,"vsParam":["-4","2","0.5","0"]},{"eOrder":18,"vsParam":["4","アニスヒソップ","ふふっ、流石[px]さんの作った道具。\r\n効果てきめんですね……！","1"]},{"eOrder":69,"vsParam":["-1019","10","1","0"]},{"eOrder":18,"vsParam":["1019","キャットニップ","ありがとにゃ～♪　とってもとっても感謝なのにゃ～♪\r\nでは、今の気持ちを一曲～♪","0"]},{"eOrder":69,"vsParam":["-1019","0","0","0"]},{"eOrder":69,"vsParam":["-1019","1","0","0"]},{"eOrder":18,"vsParam":["1019","キャットニップ","てきと～に釣り糸を垂らしたら～♪\r\nマグロがたくさん、にゃっ、にゃっ、にゃ～♪","0"]},{"eOrder":69,"vsParam":["-1019","0","0","0"]},{"eOrder":69,"vsParam":["-1019","7","1","0"]},{"eOrder":18,"vsParam":["1019","キャットニップ","大漁、大漁、嬉しいにゃ～♪\r\n嬉しいにゃったら、嬉しいにゃ～♪　にゃっ♪","0"]},{"eOrder":69,"vsParam":["-6","2","0.5","0"]},{"eOrder":18,"vsParam":["6","アンゼリカ","……それはよかったにゃ","0"]},{"eOrder":69,"vsParam":["-3","9","1","0"]},{"eOrder":18,"vsParam":["3","ソレル","……そっか、歌詞だわ！\r\nなんかピンと来なかったのよね","0"]},{"eOrder":69,"vsParam":["-1019","6","1","0"]},{"eOrder":18,"vsParam":["1019","キャットニップ","にゃ？　歌詞……？\r\n歌詞がどうかしたのかにゃ？","0"]},{"eOrder":69,"vsParam":["-3","2","0.5","0"]},{"eOrder":18,"vsParam":["3","ソレル","キャットニップって、歌はとっても上手いのよ。\r\nでも、どうしてこんなに微妙な空気になるかって言うと……","0"]},{"eOrder":69,"vsParam":["-3","11","0","0"]},{"eOrder":18,"vsParam":["3","ソレル","歌詞よ！　歌詞がいまひとつなんだわ！\r\nそこさえどうにかすれば…きっとトップを狙えるわよ！","1"]},{"eOrder":69,"vsParam":["-3","0","0","0"]},{"eOrder":69,"vsParam":["-1019","9","1","0"]},{"eOrder":18,"vsParam":["1019","キャットニップ","ズ、ズバッと来たにゃ……。\r\nまるでタチウオのごとき切れ味にゃ……","0"]},{"eOrder":69,"vsParam":["-5","8","1","0"]},{"eOrder":18,"vsParam":["5","クレソン","まぁ……うん。\r\n歌詞が……ってのはわからなくもない","3"]},{"eOrder":69,"vsParam":["-1019","5","1","0"]},{"eOrder":18,"vsParam":["1019","キャットニップ","うー。実はそれ、わりとみんなに言われるにゃ。\r\nお前は歌詞をどうにかすれば、もっと上を目指せるって","0"]},{"eOrder":69,"vsParam":["-1019","7","1","0"]},{"eOrder":18,"vsParam":["1019","キャットニップ","でも、あたしは上に行くことに興味がないにゃ。\r\nとにかく毎日歌ってれば、人生バラ色にゃんだから","0"]},{"eOrder":69,"vsParam":["-1019","10","1","0"]},{"eOrder":18,"vsParam":["1019","キャットニップ","というわけだから～♪\r\nあたしは今日も～♪　自由気ままに歌うのにゃ～♪","0"]},{"eOrder":69,"vsParam":["-4","6","1","0"]},{"eOrder":18,"vsParam":["4","アニスヒソップ","なるほど……。歌っていれば幸せ、ですか……。\r\nそういう考え方もあるんですね……","2"]},{"eOrder":69,"vsParam":["-3","2","0.5","0"]},{"eOrder":18,"vsParam":["3","ソレル","ええ、そうね。\r\nふふっ、確かに、そっちの方がキャットニップらしいかも！","1"]},{"eOrder":8,"vsParam":["1"]},{"eOrder":23,"vsParam":["1"]},{"eOrder":20,"vsParam":["「これからも歌い続けて」","「確かに『らしい』にゃ」"]},{"eOrder":21,"vsParam":["1"]},{"eOrder":69,"vsParam":["-1","7","1","1"]},{"eOrder":69,"vsParam":["-1019","7","1","0"]},{"eOrder":18,"vsParam":["1019","キャットニップ","にゃ～、あたしにお任せにゃ～！\r\nいろんな場所に、あたしの歌を届けてみせるのにゃ～♪","0"]},{"eOrder":21,"vsParam":["2"]},{"eOrder":69,"vsParam":["-1","2","0.5","1"]},{"eOrder":69,"vsParam":["-1019","7","1","0"]},{"eOrder":18,"vsParam":["1019","キャットニップ","自分でもそう思うにゃ～♪　あたしはこれからも、\r\nいろんな場所に、あたしの歌を届けてみせるのにゃ～♪","0"]},{"eOrder":22,"vsParam":[]},{"eOrder":26,"vsParam":[]},{"eOrder":20,"vsParam":["「これからも歌い続けてね！」","「確かに『らしい』にゃ」"]},{"eOrder":21,"vsParam":["1"]},{"eOrder":69,"vsParam":["-1","7","1","1"]},{"eOrder":69,"vsParam":["-1019","7","1","0"]},{"eOrder":18,"vsParam":["1019","キャットニップ","にゃ～、あたしにお任せにゃ～！\r\nいろんな場所に、あたしの歌を届けてみせるのにゃ～♪","0"]},{"eOrder":21,"vsParam":["2"]},{"eOrder":69,"vsParam":["-1","2","0.5","1"]},{"eOrder":69,"vsParam":["-1019","7","1","0"]},{"eOrder":18,"vsParam":["1019","キャットニップ","自分でもそう思うにゃ～♪　あたしはこれからも、\r\nいろんな場所に、あたしの歌を届けてみせるのにゃ～♪","0"]},{"eOrder":22,"vsParam":[]},{"eOrder":27,"vsParam":[]},{"eOrder":69,"vsParam":["-1019","10","1","0"]},{"eOrder":18,"vsParam":["1019","キャットニップ","だから、みんな～。\r\nこれからもどうぞ、よ～ろ～し～く～にゃ～♪","0"]},{"eOrder":8,"vsParam":["1"]},{"eOrder":92,"vsParam":["0"]},{"eOrder":1,"vsParam":["0"]},{"eOrder":97,"vsParam":["1"]},{"eOrder":89,"vsParam":["1"]},{"eOrder":59,"vsParam":["0","-1"]},{"eOrder":59,"vsParam":["0","-3"]},{"eOrder":59,"vsParam":["0","-4"]},{"eOrder":59,"vsParam":["0","-5"]},{"eOrder":59,"vsParam":["0","-6"]},{"eOrder":59,"vsParam":["0","-1019"]},{"eOrder":1,"vsParam":["1"]}]}
