{"m_GameObject":{"m_FileID":0,"m_PathID":0},"m_Enabled":1,"m_Script":{"m_FileID":0,"m_PathID":6520365622649918000},"m_Name":"CQ_SOL_005_010","vOrderList":[{"eOrder":4,"vsParam":["26"]},{"eOrder":95,"vsParam":["33"]},{"eOrder":18,"vsParam":["3","Sorel","Hmm...\nIf I adopt this method, then I need to use this formula...","","1"]},{"eOrder":18,"vsParam":["1010","Peppermint","Hmm... What's wrong with Sorel?\nShe's reading a reference book of wizardology, right!?","3","","6"]},{"eOrder":18,"vsParam":["4","Anis Hyssop","I am not sure... But Sorel is studying,\ncould it be an omen of something really bad!?","4","","6"]},{"eOrder":18,"vsParam":["3","Sorel","Hey, you! I heard that!\nI'll study wizardry hard, okay!","","1"]},{"eOrder":20,"vsParam":["What are you studying?","Is it required for the next lesson?"]},{"eOrder":21,"vsParam":["1"]},{"eOrder":18,"vsParam":["3","Sorel","Er, I am studying the wind wizardry.\nI'll be able to fly when I master this wizardry!","","1"]},{"eOrder":21,"vsParam":["2"]},{"eOrder":18,"vsParam":["3","Sorel","No, it's not for my lesson...\nI am studying the wind wizardry. If I master it, I'll be able to fly!","","1"]},{"eOrder":22,"vsParam":[]},{"eOrder":18,"vsParam":["5","Cresson","Oh, fly...\nSounds interesting!","1"]},{"eOrder":18,"vsParam":["3","Sorel","Right? But I haven't succeeded not even once.\nI couldn't imagine the feeling of flying in the sky...","","1"]},{"eOrder":18,"vsParam":["1010","Peppermint","Er, imagine?\nWhy would you imagine?","4","","2"]},{"eOrder":18,"vsParam":["4","Anis Hyssop","Er... The key to launch a wizardry,\nis to imagine the picture of using the wizardry in your mind...","1"]},{"eOrder":18,"vsParam":["4","Anis Hyssop","Let's take fire wizardry as an example, you have to imagine the\npicture of lighting a fire. And for the flying wizardry, you have\nto imagine yourself flying in the sky.","2"]},{"eOrder":18,"vsParam":["1010","Peppermint","Hmm~? Isn't this very easy to imagine?\nJust flap to fly, flap, flap.","0"]},{"eOrder":18,"vsParam":["4","Anis Hyssop","Ha-ha, that's because you have wings...\nIs there a way to fly without wings?","1"]},{"eOrder":18,"vsParam":["3","Sorel","Without wings... Ah, right!\nHehehe, I've got a good idea!","","1"]},{"eOrder":18,"vsParam":["3","Sorel","Think, there's a type of monsters floating in the air, right?\nPerhaps we can find inspirations by observing them!","","1"]},{"eOrder":18,"vsParam":["5","Cresson","Uh——!? Hey, using monsters as a reference, are you serious!?\nYou'll definitely get attacked!","2"]},{"eOrder":18,"vsParam":["3","Sorel","Hmm, it's alright.\nI'll kill it if it dares attacking me.","","1"]},{"eOrder":18,"vsParam":["3","Sorel","Okay, you guys will help me, right?\nFor my wind wizardry... Please, guys!","","1"]},{"eOrder":8,"vsParam":["1"]},{"eOrder":4,"vsParam":["-1"]},{"eOrder":95,"vsParam":["0"]}]}
