{"m_GameObject":{"m_FileID":0,"m_PathID":0},"m_Enabled":1,"m_Script":{"m_FileID":0,"m_PathID":6520365622649918000},"m_Name":"SQ_SUB_005_020","vOrderList":[{"eOrder":18,"vsParam":["1010","Peppermint","Young man, here you are!\n[px] has made the paper you need!","1"]},{"eOrder":18,"vsParam":["9004","Juvenile","Oh, really! And it's of super high quality!\nOh, I really appreciate it!","0","","1"]},{"eOrder":18,"vsParam":["9004","Juvenile","You've made enough paper for me to practice\nfor quite a while! I'm saved! You're a great help!","0","","3"]},{"eOrder":18,"vsParam":["4","Anis Hyssop","Hehe, I'm glad you're happy with it.\nGreat, [px].","1","","3"]},{"eOrder":20,"vsParam":["Keep trying.","Paint for me when you make a painter!"]},{"eOrder":21,"vsParam":["1"]},{"eOrder":18,"vsParam":["9004","Juvenile","Yeah, sure!\nI will make a top-ranking painter, I promise!","0","","1"]},{"eOrder":21,"vsParam":["2"]},{"eOrder":18,"vsParam":["9004","Juvenile","Yeah, sure!\nI'll paint for you after I make a top-ranking painter!","0","","1"]},{"eOrder":22,"vsParam":[]},{"eOrder":18,"vsParam":["9004","Juvenile","Your name... is [px]? Let's work hard together to make\na great painter and a great alchemist respectively!","0"]},{"eOrder":18,"vsParam":["9004","Juvenile","See you!","0"]},{"eOrder":18,"vsParam":["3","Sorel","A great painter...?\nAs for a teenager like him, maybe he'll get somewhere.","1"]},{"eOrder":18,"vsParam":["1010","Peppermint","Haha, it's true!\n[px], don't let him overshadow you!","1","","1"]}]}
