{"m_GameObject":{"m_FileID":0,"m_PathID":0},"m_Enabled":1,"m_Script":{"m_FileID":0,"m_PathID":6520365622649918000},"m_Name":"SQ_SUB_004_020","vOrderList":[{"eOrder":18,"vsParam":["1010","Peppermint","Lady, here you are.\nThis is the wine made with alchemy!","1","","1"]},{"eOrder":18,"vsParam":["9005","Young Lady","Oh... It may be rude, but it does look like average wine...","0"]},{"eOrder":18,"vsParam":["9005","Young Lady","Forget it, the point is its bouquet and taste.\nLet me try it...","0"]},{"eOrder":18,"vsParam":["4","Anis Hyssop","*Swallow.* Are you satisfied with what we made, lady...","2"]},{"eOrder":18,"vsParam":["9005","Young Lady","I see... It tastes more mellow than that I made.\nIs it because it's made with alchemy?","0"]},{"eOrder":18,"vsParam":["9005","Young Lady","So, as for its taste... Oh, oh!\nIt's good, so good!","0","","1"]},{"eOrder":18,"vsParam":["9005","Young Lady","I can't tell you how, but it's super good!\nHeehee, it's going to make a hit!","0"]},{"eOrder":18,"vsParam":["3","Sorel","[px].\nIs she drunk?","4","","6"]},{"eOrder":18,"vsParam":["4","Anis Hyssop","Yeah...\nShe can't speak clearly...","4"]},{"eOrder":18,"vsParam":["4","Anis Hyssop","Could it be...\nWine made with alchemy got higher alcohol content?","4","","6"]},{"eOrder":18,"vsParam":["3","Sorel","Maybe this lady is a lightweight.\nAnyway...","4"]},{"eOrder":18,"vsParam":["1010","Peppermint","It's hard to tell if the wine is suitable for sale...","3"]},{"eOrder":20,"vsParam":["It's a waste of time...","We'd better not sell it for security reasons..."]},{"eOrder":21,"vsParam":["1"]},{"eOrder":18,"vsParam":["4","Anis Hyssop","Ah ha ha... Sometimes, things just don't go well...\nCheer up, [px]...","4","","6"]},{"eOrder":21,"vsParam":["2"]},{"eOrder":18,"vsParam":["4","Anis Hyssop","You're right...\nWe'll end up in trouble if people buy and drink it...","3","","7"]},{"eOrder":22,"vsParam":[]},{"eOrder":18,"vsParam":["9005","Young Lady","Heehee~ So nice~ I'm going to be rich...\nThis wine will be a hot sale... Heehee...","0","","3"]}]}
