{"m_GameObject":{"m_FileID":0,"m_PathID":0},"m_Enabled":1,"m_Script":{"m_FileID":0,"m_PathID":6520365622649918000},"m_Name":"CQ_TAN_007","vOrderList":[{"eOrder":92,"vsParam":["1"]},{"eOrder":4,"vsParam":["9"]},{"eOrder":18,"vsParam":["1010","佩帕敏特","啊，坦德利昂。\n你在巡邏嗎？","1","","1","peppermint_c3_287"]},{"eOrder":18,"vsParam":["2001","坦德利昂","對對，在巡邏啊。\n（呵欠）……","3","","7","tandrion_c3_068"]},{"eOrder":18,"vsParam":["1010","佩帕敏特","我雖然知道坦德利昂你很強，\n但你總是這麼懶散不要緊嗎？","4","","6","peppermint_c3_288"]},{"eOrder":18,"vsParam":["2001","坦德利昂","嗯，這不是很正常嗎？\n就是因為強才可以偷懶啊！","1","","1","tandrion_c3_069"]},{"eOrder":18,"vsParam":["1010","佩帕敏特","是嗎……可是你明明是隊長，這樣真的沒問題嗎？\n這麼懶散，不怕被別人超越嗎？","3","","2","peppermint_c3_289"]},{"eOrder":18,"vsParam":["2001","坦德利昂","這我哪知道……\n不過就是因為沒問題，所以才會是我來當隊長吧。","1","","","tandrion_c3_070"]},{"eOrder":18,"vsParam":["1010","佩帕敏特","但是，被部下看到你這樣子\n不太好吧？","3","","","peppermint_c3_290"]},{"eOrder":18,"vsParam":["2001","坦德利昂","或許吧。不過我想大家應該都習慣了……","3","","","tandrion_c3_071"]},{"eOrder":18,"vsParam":["2001","坦德利昂","好了，我要繼續巡邏了。\n要去哪裡睡午覺呢……","1","","3","tandrion_c3_072"]},{"eOrder":18,"vsParam":["2001","坦德利昂","（呵欠）……","3","","7","tandrion_c3_073"]},{"eOrder":8,"vsParam":["1"]},{"eOrder":6,"vsParam":["46","0"]},{"eOrder":3,"vsParam":["0.5"]},{"eOrder":6,"vsParam":["46","0"]},{"eOrder":3,"vsParam":["0.5"]},{"eOrder":6,"vsParam":["46","0"]},{"eOrder":3,"vsParam":["1"]},{"eOrder":18,"vsParam":["1010","佩帕敏特","唉……\n他不是在巡邏而是單純在偷懶吧。","4","","6","peppermint_c3_291"]},{"eOrder":20,"vsParam":["「說了也是白說……」","「那樣才好！」"]},{"eOrder":21,"vsParam":["1"]},{"eOrder":8,"vsParam":["1"]},{"eOrder":98,"vsParam":["hero_c3_074","heroine_c3_074","1"]},{"eOrder":18,"vsParam":["1010","佩帕敏特","哈哈，說得也是。","1","","","peppermint_c3_292"]},{"eOrder":21,"vsParam":["2"]},{"eOrder":8,"vsParam":["1"]},{"eOrder":98,"vsParam":["hero_c3_075","heroine_c3_075","1"]},{"eOrder":18,"vsParam":["1010","佩帕敏特","喂，[px]！？\n你怎麼可以稱讚那種人！","2","","1","peppermint_c3_293"]},{"eOrder":22,"vsParam":[]},{"eOrder":18,"vsParam":["1010","佩帕敏特","唔……雖然對他的實力有疑問，\n不過我更懷疑他有沒有當隊長的自覺呢……","3","","6","peppermint_c3_294"]},{"eOrder":8,"vsParam":["1"]},{"eOrder":4,"vsParam":["-1"]},{"eOrder":92,"vsParam":["0"]}]}
