{"m_GameObject":{"m_FileID":0,"m_PathID":0},"m_Enabled":1,"m_Script":{"m_FileID":0,"m_PathID":6520365622649918000},"m_Name":"EV_036_012_010","vOrderList":[{"eOrder":18,"vsParam":["4","アニスヒソップ","『まずは古の魂（ソウル）に触れよ。\n加えて、野生の技術（テクニック）を身につけよ』","0"]},{"eOrder":18,"vsParam":["4","アニスヒソップ","『大食い虎の巻』に書かれていた\n最初の内容はこなしましたね。次は……ええっ！？","3"]},{"eOrder":18,"vsParam":["5","クレソン","ど、どうしたんだ、アニス！\n『虎の巻』にはなんて書いてあるんだ！？","2"]},{"eOrder":18,"vsParam":["4","アニスヒソップ","『魂に触れ、技術を身につけたならば……\nひたすら喰らえ』だそうです","3"]},{"eOrder":18,"vsParam":["5","クレソン","放任主義か！","2"]},{"eOrder":18,"vsParam":["3","ソレル","あはは……。\nでも、書いてあることは真理だと思うわ","0"]},{"eOrder":18,"vsParam":["3","ソレル","魂に触れて、技術を身につければ……\nあとはもう実戦あるのみ、でしょ？","1"]},{"eOrder":18,"vsParam":["5","クレソン","そりゃそうかもしれないが……","3"]},{"eOrder":18,"vsParam":["1010","ペパーミント","まぁいいんじゃない？\n要するに、好きなものを食べまくればいいんでしょ？","1"]},{"eOrder":18,"vsParam":["3","ソレル","そういうこと～♪\nうーん、なんて幸せな訓練なのかしら","1"]},{"eOrder":18,"vsParam":["5","クレソン","本当に訓練になるのか……？\nちょっと疑わしいが……いいや","3"]},{"eOrder":18,"vsParam":["5","クレソン","で、ソレル。\n何か食べたいものは……","0"]},{"eOrder":18,"vsParam":["3","ソレル","肉！！","2"]},{"eOrder":18,"vsParam":["5","クレソン","即答かよ！","2"]},{"eOrder":18,"vsParam":["3","ソレル","ふふふ……あたしが身につけた野生のテクニックが、\n肉を喰らえと囁くのよ……！","1"]},{"eOrder":18,"vsParam":["3","ソレル","さぁ、美味しいお肉の情報を集めるわよ！\nお肉をいっぱい食べることで、あたしは成長するんだから！","1"]},{"eOrder":18,"vsParam":["4","アニスヒソップ","はいはい、わかりましたわかりました。\nみんなで手分けして探すとしましょう","0"]},{"eOrder":18,"vsParam":["3","ソレル","やった～！　ふふっ、楽しみ～♪\nどんなお肉が食べられるのかしら～！","1"]},{"eOrder":18,"vsParam":["5025","オーゼイユ","……ふふっ","0"]}]}
