{"m_GameObject":{"m_FileID":0,"m_PathID":0},"m_Enabled":1,"m_Script":{"m_FileID":0,"m_PathID":6520365622649918000},"m_Name":"MQ_35_030","vOrderList":[{"eOrder":92,"vsParam":["0"]},{"eOrder":1,"vsParam":["0","1","1","0"]},{"eOrder":89,"vsParam":["0"]},{"eOrder":59,"vsParam":["1","-1","1","2.1","0.04499912","16.61","0"]},{"eOrder":59,"vsParam":["1","-3","3","0.67","0.04499912","16.3","0"]},{"eOrder":59,"vsParam":["1","-5","5","3.55","0.04499912","15.37","0"]},{"eOrder":59,"vsParam":["1","-7","7","0.21","0.04499912","14.29","0"]},{"eOrder":59,"vsParam":["1","-8","8","1.86","0.04499912","13.65","0"]},{"eOrder":59,"vsParam":["1","-9","9","1.31","0.04499912","15.22","0"]},{"eOrder":59,"vsParam":["1","-1020","1020","3","0.04499912","17.77","-155.45"]},{"eOrder":59,"vsParam":["1","-3003","3003","4.03","0.04499912","18.11","-139"]},{"eOrder":66,"vsParam":["-1","2","-1020","0","0"]},{"eOrder":66,"vsParam":["-3","2","-1020","0","0"]},{"eOrder":66,"vsParam":["-5","2","-1020","0","0"]},{"eOrder":66,"vsParam":["-7","2","-1020","0","0"]},{"eOrder":66,"vsParam":["-8","2","-1020","0","0"]},{"eOrder":66,"vsParam":["-9","2","-1020","1","0"]},{"eOrder":69,"vsParam":["-1","11","0","0"]},{"eOrder":69,"vsParam":["-3","11","0","0"]},{"eOrder":69,"vsParam":["-5","11","0","0"]},{"eOrder":69,"vsParam":["-7","11","0","0"]},{"eOrder":69,"vsParam":["-8","11","0","0"]},{"eOrder":69,"vsParam":["-9","11","0","1"]},{"eOrder":94,"vsParam":["2","-7","1"]},{"eOrder":4,"vsParam":["33"]},{"eOrder":1,"vsParam":["1","1","1","0"]},{"eOrder":92,"vsParam":["1"]},{"eOrder":69,"vsParam":["-1020","9","1","0"]},{"eOrder":18,"vsParam":["1020","暗黑高修","可惡！\n我的弟兄們！！！！！","0","","6","453"]},{"eOrder":69,"vsParam":["-1","0","0","0"]},{"eOrder":69,"vsParam":["-3","0","0","0"]},{"eOrder":69,"vsParam":["-5","0","0","0"]},{"eOrder":69,"vsParam":["-7","0","0","0"]},{"eOrder":69,"vsParam":["-8","0","0","0"]},{"eOrder":69,"vsParam":["-9","0","0","0"]},{"eOrder":69,"vsParam":["-3","7","1","0"]},{"eOrder":18,"vsParam":["3","索蕾爾","只剩下你一個人了，高修！\n快，把蘭還給我們！","2","","1","0454"]},{"eOrder":69,"vsParam":["-1020","11","0","0"]},{"eOrder":18,"vsParam":["1020","暗黑高修","我知道了，放了她就行了吧，放了她！！","0","","6","455"]},{"eOrder":69,"vsParam":["-1020","0","0","0"]},{"eOrder":18,"vsParam":["3003","蘭","夏目！！","0","","1","0456"]},{"eOrder":8,"vsParam":["1"]},{"eOrder":60,"vsParam":["-3003","2.26","0.04499912","14.96","3","1","0"]},{"eOrder":66,"vsParam":["-3003","2","-9","1","0.2"]},{"eOrder":66,"vsParam":["-9","2","-3003","1","0.2"]},{"eOrder":69,"vsParam":["-9","11","0","0"]},{"eOrder":18,"vsParam":["9","夏目","蘭，沒事吧！？\n沒受傷吧！？","2","","","457"]},{"eOrder":69,"vsParam":["-9","0","0","0"]},{"eOrder":69,"vsParam":["-3003","2","0.5","0"]},{"eOrder":18,"vsParam":["3003","蘭","嗯，我沒事……\n對不起……還有，謝謝你們能來……","3","","","0458"]},{"eOrder":69,"vsParam":["-1020","7","1","0"]},{"eOrder":18,"vsParam":["1020","暗黑高修","嘁——還在我眼前演這麼一出情誼深厚！\n這世上充滿了麻煩的傢伙，可惡！！","0","","5","459"]},{"eOrder":66,"vsParam":["-9","2","-1020","0","0.3"]},{"eOrder":66,"vsParam":["-3003","2","-1020","0","0.3"]},{"eOrder":20,"vsParam":["「抓了人，還敢說這種話……！」","「麻煩的傢伙是你吧！」"]},{"eOrder":21,"vsParam":["1"]},{"eOrder":8,"vsParam":["1"]},{"eOrder":69,"vsParam":["-1","11","1","0"]},{"eOrder":98,"vsParam":["0460_1","0461_1","1"]},{"eOrder":21,"vsParam":["2"]},{"eOrder":8,"vsParam":["1"]},{"eOrder":69,"vsParam":["-1","11","1","0"]},{"eOrder":98,"vsParam":["0462","0463","1"]},{"eOrder":22,"vsParam":[]},{"eOrder":69,"vsParam":["-1020","8","1","0"]},{"eOrder":18,"vsParam":["1020","暗黑高修","……啊——你，\n是叫[px]吧？","0","","","464"]},{"eOrder":8,"vsParam":["1"]},{"eOrder":4,"vsParam":["29"]},{"eOrder":94,"vsParam":["2","-1020","0"]},{"eOrder":12,"vsParam":["1","10","0"]},{"eOrder":23,"vsParam":["1"]},{"eOrder":95,"vsParam":["116"]},{"eOrder":26,"vsParam":[]},{"eOrder":95,"vsParam":["117"]},{"eOrder":27,"vsParam":[]},{"eOrder":12,"vsParam":["0","18","1"]},{"eOrder":94,"vsParam":["2","-7","1"]},{"eOrder":18,"vsParam":["1010","佩帕敏特","……唔！ 怎、怎麼回事……？\n這傢伙身上的氛圍，突然變了……","3","","1","0465"]},{"eOrder":18,"vsParam":["1020","暗黑高修","對我來說，你特別麻煩……\n應該說是擋到我的路了。我啊，討厭煉金術士","0","","","466"]},{"eOrder":18,"vsParam":["1020","暗黑高修","要是讓你獲得力量，就會變得很麻煩。\n不過，也只是有點麻煩，世界毀滅這個事實是不會有任何改變的","0","","","467"]},{"eOrder":8,"vsParam":["1"]},{"eOrder":95,"vsParam":["0"]},{"eOrder":69,"vsParam":["-1020","10","1","0"]},{"eOrder":18,"vsParam":["1020","暗黑高修","總之……\n你們給我記住，等下次見面，呵呵！哇哈哈哈哈哈哈哈！","0","","3","468"]},{"eOrder":8,"vsParam":["1"]},{"eOrder":1,"vsParam":["0","0","0.5","1"]},{"eOrder":69,"vsParam":["-1020","7","0.3","1"]},{"eOrder":6,"vsParam":["107","0"]},{"eOrder":79,"vsParam":["9","3","0.04499912","17.77"]},{"eOrder":59,"vsParam":["0","-1020","1020"]},{"eOrder":1,"vsParam":["1","1","1.5","1"]},{"eOrder":69,"vsParam":["-3","9","1","0"]},{"eOrder":18,"vsParam":["3","索蕾爾","啊！？\n不、不許走……可惡，跑掉了……！","4","","1","0469"]},{"eOrder":4,"vsParam":["フラーレスのダンジョン"]},{"eOrder":69,"vsParam":["-7","8","1","0"]},{"eOrder":18,"vsParam":["7","瓦萊裡安","嘁，逃跑的本事倒是不輸給任何人……\n而且還說了一堆意義不明的話……","2","","7","0470"]},{"eOrder":66,"vsParam":["-8","2","-3003","0","0.3"]},{"eOrder":69,"vsParam":["-8","1","0","0"]},{"eOrder":18,"vsParam":["8","艾麗嘉","……現在不是想這個的時候。\n總之，蘭沒事真是太好了","0","","","471"]},{"eOrder":69,"vsParam":["-8","0","0","0"]},{"eOrder":66,"vsParam":["-1","2","-3003","0","0.3"]},{"eOrder":66,"vsParam":["-3","2","-3003","0","0.3"]},{"eOrder":66,"vsParam":["-5","2","-3003","0","0.3"]},{"eOrder":66,"vsParam":["-7","2","-3003","0","0.3"]},{"eOrder":66,"vsParam":["-9","2","-3003","0","0.3"]},{"eOrder":66,"vsParam":["-3003","2","-8","0","0.3"]},{"eOrder":69,"vsParam":["-3003","2","0.5","0"]},{"eOrder":18,"vsParam":["3003","蘭","唔……\n對不起，大家……","3","","","0473"]},{"eOrder":18,"vsParam":["1010","佩帕敏特","高修……那傢伙到底是怎麼回事……\n剛才有一瞬間突然變了個人一樣……","4","","","0474"]},{"eOrder":18,"vsParam":["1010","佩帕敏特","我說[px]……\n必須要小心那傢伙才行……！","0","","","0475"]},{"eOrder":20,"vsParam":["「我知道的，放心」"]},{"eOrder":21,"vsParam":["1"]},{"eOrder":8,"vsParam":["1"]},{"eOrder":69,"vsParam":["-1","7","1","0"]},{"eOrder":98,"vsParam":["0476","0477_1","1"]},{"eOrder":22,"vsParam":[]},{"eOrder":18,"vsParam":["1010","佩帕敏特","嗯……你知道就好……\n不知道為什麼，我有種非常不詳的預感……","3","","","0478"]},{"eOrder":8,"vsParam":["1"]},{"eOrder":92,"vsParam":["0"]},{"eOrder":1,"vsParam":["0","1","1","0"]},{"eOrder":59,"vsParam":["0","-1","1"]},{"eOrder":59,"vsParam":["0","-3","3"]},{"eOrder":59,"vsParam":["0","-5","5"]},{"eOrder":59,"vsParam":["0","-7","7"]},{"eOrder":59,"vsParam":["0","-8","8"]},{"eOrder":59,"vsParam":["0","-9","9"]},{"eOrder":59,"vsParam":["0","-3003","3003"]},{"eOrder":89,"vsParam":["1"]},{"eOrder":1,"vsParam":["1","1","1","0"]}]}
