{"m_GameObject":{"m_FileID":0,"m_PathID":0},"m_Enabled":1,"m_Script":{"m_FileID":0,"m_PathID":-4874652655563781000},"m_Name":"fieldName","List":[{"iAreaNameId":1,"strAreaName":"オルビュース","strAreaNameSub":"白き芽吹きの地"},{"iAreaNameId":2,"strAreaName":"ルフナ","strAreaNameSub":""},{"iAreaNameId":3,"strAreaName":"迷いの森","strAreaNameSub":""},{"iAreaNameId":4,"strAreaName":"妖精郷","strAreaNameSub":"常春の七彩"},{"iAreaNameId":5,"strAreaName":"白蓮池","strAreaNameSub":""},{"iAreaNameId":6,"strAreaName":"リブルム","strAreaNameSub":"風雅なる紅"},{"iAreaNameId":7,"strAreaName":"ローサ=メイズ","strAreaNameSub":""},{"iAreaNameId":8,"strAreaName":"ウーファ","strAreaNameSub":""},{"iAreaNameId":9,"strAreaName":"ローズヒップ邸","strAreaNameSub":""},{"iAreaNameId":10,"strAreaName":"アーテリア","strAreaNameSub":"黒き鉱脈"},{"iAreaNameId":11,"strAreaName":"ルーゲント","strAreaNameSub":"白銀の王座"},{"iAreaNameId":12,"strAreaName":"エルレウム","strAreaNameSub":"青き海唄"},{"iAreaNameId":13,"strAreaName":"フラーレス","strAreaNameSub":"金の木漏れ日"},{"iAreaNameId":14,"strAreaName":"カヌス","strAreaNameSub":"灰の絶佳"},{"iAreaNameId":15,"strAreaName":"リンド=ザスビア","strAreaNameSub":""},{"iAreaNameId":16,"strAreaName":"アーラの煉獄","strAreaNameSub":""},{"iAreaNameId":17,"strAreaName":"ケルサの天剣","strAreaNameSub":""},{"iAreaNameId":18,"strAreaName":"ゴブリンの巣穴","strAreaNameSub":""},{"iAreaNameId":19,"strAreaName":"茨の結界","strAreaNameSub":""},{"iAreaNameId":20,"strAreaName":"茨の結界（チャレンジ）","strAreaNameSub":"　"},{"iAreaNameId":21,"strAreaName":"ルーペス廃鉱","strAreaNameSub":""},{"iAreaNameId":22,"strAreaName":"ダルダラ団アジト","strAreaNameSub":""},{"iAreaNameId":23,"strAreaName":"天地の眼","strAreaNameSub":"　"},{"iAreaNameId":24,"strAreaName":"白銀の檻","strAreaNameSub":"　"},{"iAreaNameId":25,"strAreaName":"アーテルトンネル","strAreaNameSub":"　"},{"iAreaNameId":26,"strAreaName":"妖精郷","strAreaNameSub":"常春の七彩"},{"iAreaNameId":27,"strAreaName":"海底神殿アエス・レギア","strAreaNameSub":"　"},{"iAreaNameId":28,"strAreaName":"煌めく小山","strAreaNameSub":"　"},{"iAreaNameId":29,"strAreaName":"商館","strAreaNameSub":"スカルキャップの館"},{"iAreaNameId":30,"strAreaName":"ラクタス","strAreaNameSub":""},{"iAreaNameId":31,"strAreaName":"ピスク","strAreaNameSub":""},{"iAreaNameId":32,"strAreaName":"黄金の果樹園","strAreaNameSub":""},{"iAreaNameId":33,"strAreaName":"キノコの大地","strAreaNameSub":""},{"iAreaNameId":34,"strAreaName":"リブルムの小道1","strAreaNameSub":""},{"iAreaNameId":35,"strAreaName":"リブルムの小道2","strAreaNameSub":""},{"iAreaNameId":36,"strAreaName":"リブルムの小道3","strAreaNameSub":""},{"iAreaNameId":37,"strAreaName":"人魚岩","strAreaNameSub":""},{"iAreaNameId":38,"strAreaName":"ラピス海岸・潮道","strAreaNameSub":""},{"iAreaNameId":39,"strAreaName":"カナリス海岸・潮道","strAreaNameSub":""},{"iAreaNameId":40,"strAreaName":"オレガノの小屋","strAreaNameSub":""},{"iAreaNameId":41,"strAreaName":"ラクタス街道","strAreaNameSub":""},{"iAreaNameId":42,"strAreaName":"ラクタス郊外広場","strAreaNameSub":""},{"iAreaNameId":43,"strAreaName":"ラピス海岸","strAreaNameSub":""},{"iAreaNameId":44,"strAreaName":"カナリス海岸","strAreaNameSub":""},{"iAreaNameId":45,"strAreaName":"ピスク海岸","strAreaNameSub":""},{"iAreaNameId":46,"strAreaName":"滝の裏の洞窟","strAreaNameSub":""},{"iAreaNameId":47,"strAreaName":"ころりん穴","strAreaNameSub":""},{"iAreaNameId":48,"strAreaName":"学問の道","strAreaNameSub":""},{"iAreaNameId":49,"strAreaName":"治定の道","strAreaNameSub":""},{"iAreaNameId":50,"strAreaName":"アルダ","strAreaNameSub":""},{"iAreaNameId":51,"strAreaName":"アルダの分かれ道","strAreaNameSub":""},{"iAreaNameId":52,"strAreaName":"テスト1","strAreaNameSub":""},{"iAreaNameId":53,"strAreaName":"テスト2","strAreaNameSub":""},{"iAreaNameId":54,"strAreaName":"ケルサの天剣","strAreaNameSub":""},{"iAreaNameId":55,"strAreaName":"グラキア＝カテナ","strAreaNameSub":""},{"iAreaNameId":56,"strAreaName":"トルトラ雪洞","strAreaNameSub":""},{"iAreaNameId":57,"strAreaName":"ケルサの天剣道中","strAreaNameSub":""},{"iAreaNameId":58,"strAreaName":"ギド","strAreaNameSub":""},{"iAreaNameId":59,"strAreaName":"オ・ジェーロ","strAreaNameSub":""},{"iAreaNameId":10101,"strAreaName":"鏡界オルビュース","strAreaNameSub":""},{"iAreaNameId":10102,"strAreaName":"鏡界ルフナ前","strAreaNameSub":""},{"iAreaNameId":10103,"strAreaName":"鏡界迷いの森","strAreaNameSub":""},{"iAreaNameId":10104,"strAreaName":"鏡界妖精郷","strAreaNameSub":""},{"iAreaNameId":10105,"strAreaName":"鏡界白蓮池","strAreaNameSub":""},{"iAreaNameId":10106,"strAreaName":"鏡界アカデミー前","strAreaNameSub":""},{"iAreaNameId":10206,"strAreaName":"鏡界リブルム","strAreaNameSub":""},{"iAreaNameId":10234,"strAreaName":"鏡界リブルムの小道1","strAreaNameSub":""},{"iAreaNameId":10235,"strAreaName":"鏡界リブルムの小道2","strAreaNameSub":""},{"iAreaNameId":10236,"strAreaName":"鏡界リブルムの小道3","strAreaNameSub":""},{"iAreaNameId":10237,"strAreaName":"薔薇の庭園","strAreaNameSub":""},{"iAreaNameId":10238,"strAreaName":"白亜の宮殿","strAreaNameSub":""},{"iAreaNameId":20002,"strAreaName":"ゆがみの魔窟","strAreaNameSub":""},{"iAreaNameId":90,"strAreaName":"訓練場","strAreaNameSub":""},{"iAreaNameId":99,"strAreaName":"Demo2018","strAreaNameSub":""},{"iAreaNameId":10000,"strAreaName":"花の妖精郷","strAreaNameSub":""}]}
