{"m_GameObject":{"m_FileID":0,"m_PathID":0},"m_Enabled":1,"m_Script":{"m_FileID":0,"m_PathID":6520365622649918000},"m_Name":"MQ_02_015","vOrderList":[{"eOrder":1,"vsParam":["0"]},{"eOrder":97,"vsParam":["0"]},{"eOrder":62,"vsParam":["1","-1","301","14.71","0.02","-9.04"]},{"eOrder":67,"vsParam":["-1","-160","1"]},{"eOrder":1,"vsParam":["1"]},{"eOrder":94,"vsParam":["3","-1"]},{"eOrder":18,"vsParam":["4","艾妮斯索普","那就是……奧爾加諾的小屋吧？\n周圍有魔物在遊蕩……","","0","","anis_m_079"]},{"eOrder":18,"vsParam":["3","索雷爾","沒錯。\n不過……全部打倒就行了吧！","","0","","sorel_m_104"]},{"eOrder":8,"vsParam":["1"]},{"eOrder":1,"vsParam":["0"]},{"eOrder":62,"vsParam":["0","-1","301"]},{"eOrder":97,"vsParam":["1"]},{"eOrder":1,"vsParam":["1"]}]}
